Workbook

Sheet new total list
A1: Name+ company | B1: {=IF(ISBLANK(C1:C1845), "", TRIM(C1:C1845 & " " & D1:D1845))} -> Name1 Name 2 | C1: Name1 | D1: Name 2 | E1: mail | F1: company | G1: type | H1: connection | I1: 2nd | J1: Code | K1: Invite | L1: Save the date MTS 26 | M1: Registered check: ARRAYFORMULA(IF(ISNUMBER(MATCH(LOWER(TRIM(E455:E1201)),LOWER(TRIM(#REF!)), 0)), TRUE, FALSE)) | N1: =VLOOKUP(B1,'MTS 2026 registrations'!A:A,1,false) -> #N/A
A2: =B2&" "&F2 -> Aabharan Hemanth Myst Works | B2: Aabharan Hemanth | C2: Aabharan | D2: Hemanth | E2: aabharan@myst.works | F2: Myst Works | G2: Startup/founder | H2: Radena Tsoneva (YES!Delft) | J2: HNX9C7 | K2: Free | L2: Bounce | M2: =VLOOKUP(E2,'MTS 2026 registrations'!B:B,1,false) -> #N/A | N2: =VLOOKUP(B2,'MTS 2026 registrations'!A:A,1,false) -> #N/A | O2: =IF(AND(ISNA(M2), ISNA(N2)), "Marked", "") -> Marked
A3: =B3&" "&F3 -> Adnan Tunovic Mungosworks | B3: Adnan Tunovic | C3: Adnan | D3: Tunovic | E3: adnan@mungosworks.nl | F3: Mungosworks | G3: Startup/founder | H3: Radena Tsoneva (YES!Delft) | J3: XGFIJJ | K3: Free | L3: Bounce | M3: =VLOOKUP(E3,'MTS 2026 registrations'!B:B,1,false) -> #N/A | N3: =VLOOKUP(B3,'MTS 2026 registrations'!A:A,1,false) -> #N/A | O3: =IF(AND(ISNA(M3), ISNA(N3)), "Marked", "") -> Marked
A4: =B4&" "&F4 -> Ahmed Mohamedali conical | B4: Ahmed Mohamedali | C4: Ahmed | D4: Mohamedali | E4: ahmed@conical.ai | F4: conical | G4: Startup/founder | H4: Radena Tsoneva (YES!Delft) | J4: IQNFNA | K4: Free | L4: Bounce | M4: =VLOOKUP(E4,'MTS 2026 registrations'!B:B,1,false) -> #N/A | N4: =VLOOKUP(B4,'MTS 2026 registrations'!A:A,1,false) -> #N/A | O4: =IF(AND(ISNA(M4), ISNA(N4)), "Marked", "") -> Marked
A5: =B5&" "&F5 -> Ahmed Faramawy Infinipipe | B5: Ahmed Faramawy | C5: Ahmed | D5: Faramawy | E5: ahmed@infinipipe.com | F5: Infinipipe | G5: Startup/founder | H5: Radena Tsoneva (YES!Delft) | J5: PW4TW4 | K5: Free | L5: Bounce | M5: =VLOOKUP(E5,'MTS 2026 registrations'!B:B,1,false) -> #N/A | N5: =VLOOKUP(B5,'MTS 2026 registrations'!A:A,1,false) -> #N/A | O5: =IF(AND(ISNA(M5), ISNA(N5)), "Marked", "") -> Marked
A6: =B6&" "&F6 -> Akarsh Gopal Myst Works | B6: Akarsh Gopal | C6: Akarsh | D6: Gopal | E6: akarsh@myst.works | F6: Myst Works | G6: Startup/founder | H6: Radena Tsoneva (YES!Delft) | J6: H9N5CZ | K6: Free | L6: Bounce | M6: =VLOOKUP(E6,'MTS 2026 registrations'!B:B,1,false) -> #N/A | N6: =VLOOKUP(B6,'MTS 2026 registrations'!A:A,1,false) -> #N/A | O6: =IF(AND(ISNA(M6), ISNA(N6)), "Marked", "") -> Marked
A7: =B7&" "&F7 -> Akash Parmesar olympian | B7: Akash Parmesar | C7: Akash | D7: Parmesar | E7: akash@olympian.ai | F7: olympian | G7: Startup/founder | H7: Radena Tsoneva (YES!Delft) | J7: L362K9 | K7: Free | L7: Bounce | M7: =VLOOKUP(E7,'MTS 2026 registrations'!B:B,1,false) -> #N/A | N7: =VLOOKUP(B7,'MTS 2026 registrations'!A:A,1,false) -> #N/A | O7: =IF(AND(ISNA(M7), ISNA(N7)), "Marked", "") -> Marked
A8: =B8&" "&F8 -> Amir Piltan sporebi | B8: Amir Piltan | C8: Amir | D8: Piltan | E8: amir@sporebi.com | F8: sporebi | G8: Startup/founder | H8: Radena Tsoneva (YES!Delft) | J8: 18ZZQ3 | K8: Free | L8: Bounce | M8: =VLOOKUP(E8,'MTS 2026 registrations'!B:B,1,false) -> #N/A | N8: =VLOOKUP(B8,'MTS 2026 registrations'!A:A,1,false) -> #N/A | O8: =IF(AND(ISNA(M8), ISNA(N8)), "Marked", "") -> Marked
A9: =B9&" "&F9 -> Andre Cossee Anything Connected | B9: Andre Cossee | C9: Andre | D9: Cossee | E9: andre@anything-connected.com | F9: Anything Connected | G9: Startup/founder | H9: Radena Tsoneva (YES!Delft) | J9: YAHJSA | K9: Free | L9: Bounce | M9: =VLOOKUP(E9,'MTS 2026 registrations'!B:B,1,false) -> #N/A | N9: =VLOOKUP(B9,'MTS 2026 registrations'!A:A,1,false) -> #N/A | O9: =IF(AND(ISNA(M9), ISNA(N9)), "Marked", "") -> Marked
A10: =B10&" "&F10 -> Andreas Schmidt-Ott tudelft | B10: Andreas Schmidt-Ott | C10: Andreas | D10: Schmidt-Ott | E10: a.schmidt-ott@tudelft.nl | F10: tudelft | G10: Startup/founder | H10: Radena Tsoneva (YES!Delft) | J10: 352ASR | K10: Free | L10: Bounce | M10: =VLOOKUP(E10,'MTS 2026 registrations'!B:B,1,false) -> #N/A | N10: =VLOOKUP(B10,'MTS 2026 registrations'!A:A,1,false) -> #N/A | O10: =IF(AND(ISNA(M10), ISNA(N10)), "Marked", "") -> Marked
A11: =B11&" "&F11 -> Angelique Nederlof rdgg | B11: Angelique Nederlof | C11: Angelique | D11: Nederlof | E11: angelique.nederlof@rdgg.nl | F11: rdgg | G11: Mentor/Expert | H11: Radena Tsoneva (YES!Delft) | J11: XBDDWW | K11: Free | L11: Bounce | M11: =VLOOKUP(E11,'MTS 2026 registrations'!B:B,1,false) -> #N/A | N11: =VLOOKUP(B11,'MTS 2026 registrations'!A:A,1,false) -> #N/A | O11: =IF(AND(ISNA(M11), ISNA(N11)), "Marked", "") -> Marked
A12: =B12&" "&F12 -> Anthony Thirkettle giaura | B12: Anthony Thirkettle | C12: Anthony | D12: Thirkettle | E12: anthony@giaura.com | F12: giaura | G12: Startup/founder | H12: Radena Tsoneva (YES!Delft) | J12: BBGHLD | K12: Free | L12: Bounce | M12: =VLOOKUP(E12,'MTS 2026 registrations'!B:B,1,false) -> #N/A | N12: =VLOOKUP(B12,'MTS 2026 registrations'!A:A,1,false) -> #N/A | O12: =IF(AND(ISNA(M12), ISNA(N12)), "Marked", "") -> Marked
A13: =B13&" "&F13 -> Arjan Oudshoorn delftab | B13: Arjan Oudshoorn | C13: Arjan | D13: Oudshoorn | E13: oudshoorn@delftab.com | F13: delftab | G13: Startup/founder | H13: Radena Tsoneva (YES!Delft) | J13: 5QSHU1 | K13: Free | L13: Bounce | M13: =VLOOKUP(E13,'MTS 2026 registrations'!B:B,1,false) -> #N/A | N13: =VLOOKUP(B13,'MTS 2026 registrations'!A:A,1,false) -> #N/A | O13: =IF(AND(ISNA(M13), ISNA(N13)), "Marked", "") -> Marked
... A24: =B24&" "&F24 -> Chandler hatton SimGas | B24: Chandler hatton | C24: Chandler | D24: hatton | E24: chandlerhatton@simgas.org | F24: SimGas | G24: Startup/founder | H24: Radena Tsoneva (YES!Delft) | J24: YA76QZ | K24: Free | L24: Bounce | M24: =VLOOKUP(E24,'MTS 2026 registrations'!B:B,1,false) -> #N/A | N24: =VLOOKUP(B24,'MTS 2026 registrations'!A:A,1,false) -> #N/A | O24: =IF(AND(ISNA(M24), ISNA(N24)), "Marked", "") -> Marked
A25: =B25&" "&F25 -> Chris van Voorden innovationquarter | B25: Chris van Voorden | C25: Chris | D25: van Voorden | E25: chris.vanvoorden@innovationquarter.nl | F25: innovationquarter | G25: Partner | H25: Freek Smoes (YES!Delft) | I25: Horizon Flevoland | K25: NO | L25: Bounce | M25: =VLOOKUP(E25,'MTS 2026 registrations'!B:B,1,false) -> #N/A | N25: =VLOOKUP(B25,'MTS 2026 registrations'!A:A,1,false) -> #N/A | O25: =IF(AND(ISNA(M25), ISNA(N25)), "Marked", "") -> Marked
A26: =B26&" "&F26 -> Christiaan van Nispen tilercharge | B26: Christiaan van Nispen | C26: Christiaan | D26: van Nispen | E26: christiaan@tilercharge.com | F26: tilercharge | G26: Startup/founder | H26: Radena Tsoneva (YES!Delft) | J26: U9XMLU | K26: Free | L26: Bounce | M26: =VLOOKUP(E26,'MTS 2026 registrations'!B:B,1,false) -> #N/A | N26: =VLOOKUP(B26,'MTS 2026 registrations'!A:A,1,false) -> #N/A | O26: =IF(AND(ISNA(M26), ISNA(N26)), "Marked", "") -> Marked
A27: =B27&" "&F27 -> Christopher Arida diwama | B27: Christopher Arida | C27: Christopher | D27: Arida | E27: christopherarida@diwama.com | F27: diwama | G27: Startup/founder | H27: Radena Tsoneva (YES!Delft) | J27: ZCFNB9 | K27: Free | L27: Bounce | M27: =VLOOKUP(E27,'MTS 2026 registrations'!B:B,1,false) -> #N/A | N27: =VLOOKUP(B27,'MTS 2026 registrations'!A:A,1,false) -> #N/A | O27: =IF(AND(ISNA(M27), ISNA(N27)), "Marked", "") -> Marked
A28: =B28&" "&F28 -> Claire Bénard merqato | B28: Claire Bénard | C28: Claire | D28: Bénard | E28: claire@merqato.eu | F28: merqato | G28: Startup/founder | H28: Radena Tsoneva (YES!Delft) | J28: P4ZPMZ | K28: Free | L28: Bounce | M28: =VLOOKUP(E28,'MTS 2026 registrations'!B:B,1,false) -> #N/A | N28: =VLOOKUP(B28,'MTS 2026 registrations'!A:A,1,false) -> #N/A | O28: =IF(AND(ISNA(M28), ISNA(N28)), "Marked", "") -> Marked
A29: =B29&" "&F29 -> Daan Protension Composites | B29: Daan | C29: Daan | E29: daan@protension.nl | F29: Protension Composites | G29: Startup/founder | H29: Radena Tsoneva (YES!Delft) | J29: 5Z7I83 | K29: Free | L29: Bounce | M29: =VLOOKUP(E29,'MTS 2026 registrations'!B:B,1,false) -> #N/A | N29: =VLOOKUP(B29,'MTS 2026 registrations'!A:A,1,false) -> #N/A | O29: =IF(AND(ISNA(M29), ISNA(N29)), "Marked", "") -> Marked
A30: =B30&" "&F30 -> Daniël van den Bosch vibestechnology | B30: Daniël van den Bosch | C30: Daniël | D30: van den Bosch | E30: daniel@vibestechnology.com | F30: vibestechnology | G30: Startup/founder | H30: Radena Tsoneva (YES!Delft) | J30: 1137HG | K30: Free | L30: Bounce | M30: =VLOOKUP(E30,'MTS 2026 registrations'!B:B,1,false) -> #N/A | N30: =VLOOKUP(B30,'MTS 2026 registrations'!A:A,1,false) -> #N/A | O30: =IF(AND(ISNA(M30), ISNA(N30)), "Marked", "") -> Marked
A31: =B31&" "&F31 -> Dennis Saaltink CheckZis | B31: Dennis Saaltink | C31: Dennis | D31: Saaltink | E31: dennis@checkzis.com | F31: CheckZis | G31: Startup/founder | H31: Radena Tsoneva (YES!Delft) | J31: WSBHKJ | K31: Free | L31: Bounce | M31: =VLOOKUP(E31,'MTS 2026 registrations'!B:B,1,false) -> #N/A | N31: =VLOOKUP(B31,'MTS 2026 registrations'!A:A,1,false) -> #N/A | O31: =IF(AND(ISNA(M31), ISNA(N31)), "Marked", "") -> Marked
A32: =B32&" "&F32 -> Dirk Dokter atmosuav | B32: Dirk Dokter | C32: Dirk | D32: Dokter | E32: dirk.dokter@atmosuav.com | F32: atmosuav | G32: Startup/founder | H32: Radena Tsoneva (YES!Delft) | J32: C8IZUC | K32: Free | L32: Bounce | M32: =VLOOKUP(E32,'MTS 2026 registrations'!B:B,1,false) -> #N/A | N32: =VLOOKUP(B32,'MTS 2026 registrations'!A:A,1,false) -> #N/A | O32: =IF(AND(ISNA(M32), ISNA(N32)), "Marked", "") -> Marked
A33: =B33&" "&F33 -> E. Geertsema antoniusziekenhuis | B33: E. Geertsema | C33: E. | D33: Geertsema | E33: e.geertsema@antoniusziekenhuis.nl | F33: antoniusziekenhuis | G33: Corporate | H33: Moshe Sijben (YES!Delft) | K33: NO | L33: Bounce | M33: =VLOOKUP(E33,'MTS 2026 registrations'!B:B,1,false) -> #N/A | N33: =VLOOKUP(B33,'MTS 2026 registrations'!A:A,1,false) -> #N/A | O33: =IF(AND(ISNA(M33), ISNA(N33)), "Marked", "") -> Marked
A34: =B34&" "&F34 -> Eduard Ijsselmuiden delftdynamics | B34: Eduard Ijsselmuiden | C34: Eduard | D34: Ijsselmuiden | E34: e.g.ijsselmuiden@delftdynamics.nl | F34: delftdynamics | G34: Startup/founder | H34: Radena Tsoneva (YES!Delft) | J34: B3KMTG | K34: Free | L34: Bounce | M34: =VLOOKUP(E34,'MTS 2026 registrations'!B:B,1,false) -> #N/A | N34: =VLOOKUP(B34,'MTS 2026 registrations'!A:A,1,false) -> #N/A | O34: =IF(AND(ISNA(M34), ISNA(N34)), "Marked", "") -> Marked
A35: =B35&" "&F35 -> Eldert Besseling campusatsea | B35: Eldert Besseling | C35: Eldert | D35: Besseling | E35: eldert.besseling@campusatsea.nl | F35: campusatsea | G35: Startup Ecosystem | H35: Moshe Sijben (YES!Delft) | K35: NO | L35: Bounce | M35: =VLOOKUP(E35,'MTS 2026 registrations'!B:B,1,false) -> #N/A | N35: =VLOOKUP(B35,'MTS 2026 registrations'!A:A,1,false) -> #N/A | O35: =IF(AND(ISNA(M35), ISNA(N35)), "Marked", "") -> Marked
A36: =B36&" "&F36 -> Emil Hernandez Renset bv | B36: Emil Hernandez | C36: Emil | D36: Hernandez | E36: emil@renset.nl | F36: Renset bv | G36: Startup/founder | H36: Radena Tsoneva (YES!Delft) | J36: QWCAL0 | K36: Free | L36: Bounce | M36: =VLOOKUP(E36,'MTS 2026 registrations'!B:B,1,false) -> #N/A | N36: =VLOOKUP(B36,'MTS 2026 registrations'!A:A,1,false) -> #N/A | O36: =IF(AND(ISNA(M36), ISNA(N36)), "Marked", "") -> Marked
A37: =B37&" "&F37 -> Ernesto Mobbr Crowd Payment | B37: Ernesto | C37: Ernesto | E37: ernesto@mobbr.com | F37: Mobbr Crowd Payment | G37: Startup/founder | H37: Radena Tsoneva (YES!Delft) | J37: K4CQ7T | K37: Free | L37: Bounce | M37: =VLOOKUP(E37,'MTS 2026 registrations'!B:B,1,false) -> #N/A | N37: =VLOOKUP(B37,'MTS 2026 registrations'!A:A,1,false) -> #N/A | O37: =IF(AND(ISNA(M37), ISNA(N37)), "Marked", "") -> Marked
A38: =B38&" "&F38 -> Esther Zandvliet arnold-siedsma | B38: Esther Zandvliet | C38: Esther | D38: Zandvliet | E38: ezandvliet@arnold-siedsma.nl | F38: arnold-siedsma | G38: Partner | H38: Radena Tsoneva (YES!Delft) | J38: XCK3K7 | K38: Free | L38: Bounce | M38: =VLOOKUP(E38,'MTS 2026 registrations'!B:B,1,false) -> #N/A | N38: =VLOOKUP(B38,'MTS 2026 registrations'!A:A,1,false) -> #N/A | O38: =IF(AND(ISNA(M38), ISNA(N38)), "Marked", "") -> Marked
A39: =B39&" "&F39 -> Evgeny EVI Safety Technology | B39: Evgeny | C39: Evgeny | E39: eshavlyugin@evist.ai | F39: EVI Safety Technology | G39: Startup/founder | H39: Pablo Benéitez (YES!Delft) | J39: O85TDB | K39: Free | L39: Bounce | M39: =VLOOKUP(E39,'MTS 2026 registrations'!B:B,1,false) -> #N/A | N39: =VLOOKUP(B39,'MTS 2026 registrations'!A:A,1,false) -> #N/A | O39: =IF(AND(ISNA(M39), ISNA(N39)), "Marked", "") -> Marked
A40: =B40&" "&F40 -> Finn Boonman olympian | B40: Finn Boonman | C40: Finn | D40: Boonman | E40: finn@olympian.ai | F40: olympian | G40: Startup/founder | H40: Radena Tsoneva (YES!Delft) | J40: U8YT8B | K40: Free | L40: Bounce | M40: =VLOOKUP(E40,'MTS 2026 registrations'!B:B,1,false) -> #N/A | N40: =VLOOKUP(B40,'MTS 2026 registrations'!A:A,1,false) -> #N/A | O40: =IF(AND(ISNA(M40), ISNA(N40)), "Marked", "") -> Marked
A41: =B41&" "&F41 -> Florent Gatin kien | B41: Florent Gatin | C41: Florent | D41: Gatin | E41: florent@kien.io | F41: kien | G41: Startup/founder | H41: Radena Tsoneva (YES!Delft) | J41: PBKKDX | K41: Free | L41: Bounce | M41: =VLOOKUP(E41,'MTS 2026 registrations'!B:B,1,false) -> #N/A | N41: =VLOOKUP(B41,'MTS 2026 registrations'!A:A,1,false) -> #N/A | O41: =IF(AND(ISNA(M41), ISNA(N41)), "Marked", "") -> Marked
A42: =B42&" "&F42 -> Frank van der Ent tribess | B42: Frank van der Ent | C42: Frank | D42: van der Ent | E42: frank.vanderent@tribess.com | F42: tribess | G42: Startup/founder | H42: Radena Tsoneva (YES!Delft) | J42: 47QEXY | K42: Free | L42: Bounce | M42: =VLOOKUP(E42,'MTS 2026 registrations'!B:B,1,false) -> #N/A | N42: =VLOOKUP(B42,'MTS 2026 registrations'!A:A,1,false) -> #N/A | O42: =IF(AND(ISNA(M42), ISNA(N42)), "Marked", "") -> Marked
A43: =B43&" "&F43 -> Gerrit Jan Van 't Veen Mills, Clay and Carpenter | B43: Gerrit Jan Van 't Veen | C43: Gerrit Jan | D43: Van 't Veen | E43: gj@dutchcoastsoftware.com | F43: Mills, Clay and Carpenter | G43: Startup/founder | H43: Radena Tsoneva (YES!Delft) | J43: R9NC86 | K43: Free | L43: Bounce | M43: =VLOOKUP(E43,'MTS 2026 registrations'!B:B,1,false) -> #N/A | N43: =VLOOKUP(B43,'MTS 2026 registrations'!A:A,1,false) -> #N/A | O43: =IF(AND(ISNA(M43), ISNA(N43)), "Marked", "") -> Marked
A44: =B44&" "&F44 -> Gunawan Kusuma 4FOLD (Holland Container Innovations) | B44: Gunawan Kusuma | C44: Gunawan | D44: Kusuma | E44: g.kusuma@hcinnovations.nl | F44: 4FOLD (Holland Container Innovations) | G44: Startup/founder | H44: Radena Tsoneva (YES!Delft) | J44: IPM4WY | K44: Free | L44: Bounce | M44: =VLOOKUP(E44,'MTS 2026 registrations'!B:B,1,false) -> #N/A | N44: =VLOOKUP(B44,'MTS 2026 registrations'!A:A,1,false) -> #N/A | O44: =IF(AND(ISNA(M44), ISNA(N44)), "Marked", "") -> Marked
A45: =B45&" "&F45 -> Hans Cool alucha | B45: Hans Cool | C45: Hans | D45: Cool | E45: hans.cool@alucha.com | F45: alucha | G45: Mentor/Expert | H45: Radena Tsoneva (YES!Delft) | K45: NO | L45: Bounce | M45: =VLOOKUP(E45,'MTS 2026 registrations'!B:B,1,false) -> #N/A | N45: =VLOOKUP(B45,'MTS 2026 registrations'!A:A,1,false) -> #N/A | O45: =IF(AND(ISNA(M45), ISNA(N45)), "Marked", "") -> Marked
A46: =B46&" "&F46 -> Hein Willems Medvice Digital Health | B46: Hein Willems | C46: Hein | D46: Willems | E46: hein@medvice.io | F46: Medvice Digital Health | G46: Startup/founder | H46: Radena Tsoneva (YES!Delft) | J46: 388QUR | K46: Free | L46: Bounce | M46: =VLOOKUP(E46,'MTS 2026 registrations'!B:B,1,false) -> #N/A | N46: =VLOOKUP(B46,'MTS 2026 registrations'!A:A,1,false) -> #N/A | O46: =IF(AND(ISNA(M46), ISNA(N46)), "Marked", "") -> Marked
A47: =B47&" "&F47 -> Helen Nofrina focalyse | B47: Helen Nofrina | C47: Helen | D47: Nofrina | E47: helen.nofrina@focalyse.com | F47: focalyse | G47: Mentor/Expert | H47: Radena Tsoneva (YES!Delft) | K47: NO | L47: Bounce | M47: =VLOOKUP(E47,'MTS 2026 registrations'!B:B,1,false) -> #N/A | N47: =VLOOKUP(B47,'MTS 2026 registrations'!A:A,1,false) -> #N/A | O47: =IF(AND(ISNA(M47), ISNA(N47)), "Marked", "") -> Marked
A48: =B48&" "&F48 -> Henk Smith OCRS smithoverseas | B48: Henk Smith | C48: Henk | D48: Smith | E48: hjsmith@smithoverseas.com | F48: OCRS smithoverseas | G48: Startup/founder | H48: Radena Tsoneva (YES!Delft) | J48: GSL7EN | K48: Free | L48: Bounce | M48: =VLOOKUP(E48,'MTS 2026 registrations'!B:B,1,false) -> #N/A | N48: =VLOOKUP(B48,'MTS 2026 registrations'!A:A,1,false) -> #N/A | O48: =IF(AND(ISNA(M48), ISNA(N48)), "Marked", "") -> Marked
A49: =B49&" "&F49 -> Iris Schut rvo | B49: Iris Schut | C49: Iris | D49: Schut | E49: iris.schut@rvo.nl | F49: rvo | G49: Startup Ecosystem | H49: Radena Tsoneva (YES!Delft) | J49: GDKWUU | K49: Free | L49: Bounce | M49: =VLOOKUP(E49,'MTS 2026 registrations'!B:B,1,false) -> #N/A | N49: =VLOOKUP(B49,'MTS 2026 registrations'!A:A,1,false) -> #N/A | O49: =IF(AND(ISNA(M49), ISNA(N49)), "Marked", "") -> Marked
A50: =B50&" "&F50 -> Isaac Kargar supplyz | B50: Isaac Kargar | C50: Isaac | D50: Kargar | E50: isaac.kargar@supplyz.eu | F50: supplyz | G50: Startup/founder | H50: Radena Tsoneva (YES!Delft) | J50: T903PS | K50: Free | L50: Bounce | M50: =VLOOKUP(E50,'MTS 2026 registrations'!B:B,1,false) -> #N/A | N50: =VLOOKUP(B50,'MTS 2026 registrations'!A:A,1,false) -> #N/A | O50: =IF(AND(ISNA(M50), ISNA(N50)), "Marked", "") -> Marked
A51: =B51&" "&F51 -> Jaap Roggeveen Gyromotics | B51: Jaap Roggeveen | C51: Jaap | D51: Roggeveen | E51: jaap.roggeveen@gyromotics.com | F51: Gyromotics | G51: Startup/founder | H51: Radena Tsoneva (YES!Delft) | J51: C6BO4F | K51: Free | L51: Bounce | M51: =VLOOKUP(E51,'MTS 2026 registrations'!B:B,1,false) -> #N/A | N51: =VLOOKUP(B51,'MTS 2026 registrations'!A:A,1,false) -> #N/A | O51: =IF(AND(ISNA(M51), ISNA(N51)), "Marked", "") -> Marked
A52: =B52&" "&F52 -> Jacky Ferdinand Henriette Wetzels Protension Composites | B52: Jacky Ferdinand Henriette Wetzels | C52: Jacky Ferdinand Henriette | D52: Wetzels | E52: jack@protension.eu | F52: Protension Composites | G52: Startup/founder | H52: Radena Tsoneva (YES!Delft) | J52: N180P9 | K52: Free | L52: Bounce | M52: =VLOOKUP(E52,'MTS 2026 registrations'!B:B,1,false) -> #N/A | N52: =VLOOKUP(B52,'MTS 2026 registrations'!A:A,1,false) -> #N/A | O52: =IF(AND(ISNA(M52), ISNA(N52)), "Marked", "") -> Marked
A53: =B53&" "&F53 -> Jan Van Kranendonk Sunuru | B53: Jan Van Kranendonk | C53: Jan | D53: Van Kranendonk | E53: jan@sunuru.net | F53: Sunuru | G53: Startup/founder | H53: Radena Tsoneva (YES!Delft) | J53: 333JDA | K53: Free | L53: Bounce | M53: =VLOOKUP(E53,'MTS 2026 registrations'!B:B,1,false) -> #N/A | N53: =VLOOKUP(B53,'MTS 2026 registrations'!A:A,1,false) -> #N/A | O53: =IF(AND(ISNA(M53), ISNA(N53)), "Marked", "") -> Marked
A54: =B54&" "&F54 -> Jasper Hartong calendar42 | B54: Jasper Hartong | C54: Jasper | D54: Hartong | E54: jasper@calendar42.com | F54: calendar42 | G54: Startup/founder | H54: Radena Tsoneva (YES!Delft) | J54: 6D66LE | K54: Free | L54: Bounce | M54: =VLOOKUP(E54,'MTS 2026 registrations'!B:B,1,false) -> #N/A | N54: =VLOOKUP(B54,'MTS 2026 registrations'!A:A,1,false) -> #N/A | O54: =IF(AND(ISNA(M54), ISNA(N54)), "Marked", "") -> Marked
A55: =B55&" "&F55 -> Jenny Inchbald meshlingerie | B55: Jenny Inchbald | C55: Jenny | D55: Inchbald | E55: jenny@meshlingerie.nl | F55: meshlingerie | G55: Startup/founder | H55: Radena Tsoneva (YES!Delft) | J55: CJL2IH | K55: Free | L55: Bounce | M55: =VLOOKUP(E55,'MTS 2026 registrations'!B:B,1,false) -> #N/A | N55: =VLOOKUP(B55,'MTS 2026 registrations'!A:A,1,false) -> #N/A | O55: =IF(AND(ISNA(M55), ISNA(N55)), "Marked", "") -> Marked
A56: =B56&" "&F56 -> Jens Bal Ephicas | B56: Jens Bal | C56: Jens | D56: Bal | E56: jens.bal@ephicas.eu | F56: Ephicas | G56: Startup/founder | H56: Radena Tsoneva (YES!Delft) | J56: WBSAM3 | K56: Free | L56: Bounce | M56: =VLOOKUP(E56,'MTS 2026 registrations'!B:B,1,false) -> #N/A | N56: =VLOOKUP(B56,'MTS 2026 registrations'!A:A,1,false) -> #N/A | O56: =IF(AND(ISNA(M56), ISNA(N56)), "Marked", "") -> Marked
A57: =B57&" "&F57 -> Jeroen Checkzis | B57: Jeroen | C57: Jeroen | E57: jeroen@checkzis.com | F57: Checkzis | G57: Startup/founder | H57: Radena Tsoneva (YES!Delft) | J57: 7FVLSQ | K57: Free | L57: Bounce | M57: =VLOOKUP(E57,'MTS 2026 registrations'!B:B,1,false) -> #N/A | N57: =VLOOKUP(B57,'MTS 2026 registrations'!A:A,1,false) -> #N/A | O57: =IF(AND(ISNA(M57), ISNA(N57)), "Marked", "") -> Marked
A58: =B58&" "&F58 -> Jeroen Schipper denhaag | B58: Jeroen Schipper | C58: Jeroen | D58: Schipper | E58: jeroen.schipper@denhaag.nl | F58: denhaag | G58: Government | H58: Moshe Sijben (YES!Delft) | J58: NAX3IS | K58: Free | L58: Bounce | M58: =VLOOKUP(E58,'MTS 2026 registrations'!B:B,1,false) -> #N/A | N58: =VLOOKUP(B58,'MTS 2026 registrations'!A:A,1,false) -> #N/A | O58: =IF(AND(ISNA(M58), ISNA(N58)), "Marked", "") -> Marked
A59: =B59&" "&F59 -> Jeroen Cevaal Polytential | B59: Jeroen Cevaal | C59: Jeroen | D59: Cevaal | E59: jeroen@polytential.eu | F59: Polytential | G59: Startup/founder | H59: Radena Tsoneva (YES!Delft) | J59: SNTERE | K59: Free | L59: Bounce | M59: =VLOOKUP(E59,'MTS 2026 registrations'!B:B,1,false) -> #N/A | N59: =VLOOKUP(B59,'MTS 2026 registrations'!A:A,1,false) -> #N/A | O59: =IF(AND(ISNA(M59), ISNA(N59)), "Marked", "") -> Marked
A60: =B60&" "&F60 -> Joep van Heesch IN-DUC | B60: Joep van Heesch | C60: Joep | D60: van Heesch | E60: info@in-duc.com | F60: IN-DUC | G60: Startup/Founder | H60: Pablo Benéitez (YES!Delft) | J60: IJAMYA | K60: Free | L60: Bounce | M60: =VLOOKUP(E60,'MTS 2026 registrations'!B:B,1,false) -> #N/A | N60: =VLOOKUP(B60,'MTS 2026 registrations'!A:A,1,false) -> #N/A | O60: =IF(AND(ISNA(M60), ISNA(N60)), "Marked", "") -> Marked
A61: =B61&" "&F61 -> Joeri Shake-on | B61: Joeri | C61: Joeri | E61: jouri@shake-on.com | F61: Shake-on | G61: Startup/founder | H61: Radena Tsoneva (YES!Delft) | J61: IUFY8G | K61: Free | L61: Bounce | M61: =VLOOKUP(E61,'MTS 2026 registrations'!B:B,1,false) -> #N/A | N61: =VLOOKUP(B61,'MTS 2026 registrations'!A:A,1,false) -> #N/A | O61: =IF(AND(ISNA(M61), ISNA(N61)), "Marked", "") -> Marked
A62: =B62&" "&F62 -> Johannes Luijten adjuvomotion | B62: Johannes Luijten | C62: Johannes | D62: Luijten | E62: j.luijten@adjuvomotion.com | F62: adjuvomotion | G62: Startup/founder | H62: Radena Tsoneva (YES!Delft) | J62: W4LWRG | K62: Free | L62: Bounce | M62: =VLOOKUP(E62,'MTS 2026 registrations'!B:B,1,false) -> #N/A | N62: =VLOOKUP(B62,'MTS 2026 registrations'!A:A,1,false) -> #N/A | O62: =IF(AND(ISNA(M62), ISNA(N62)), "Marked", "") -> Marked
A63: =B63&" "&F63 -> John Harinck Gensos | B63: John Harinck | C63: John | D63: Harinck | E63: j.harinck@gensos.nl | F63: Gensos | G63: Startup/founder | H63: Radena Tsoneva (YES!Delft) | J63: JTXI4R | K63: Free | L63: Bounce | M63: =VLOOKUP(E63,'MTS 2026 registrations'!B:B,1,false) -> #N/A | N63: =VLOOKUP(B63,'MTS 2026 registrations'!A:A,1,false) -> #N/A | O63: =IF(AND(ISNA(M63), ISNA(N63)), "Marked", "") -> Marked
A64: =B64&" "&F64 -> John Beckett vemble | B64: John Beckett | C64: John | D64: Beckett | E64: john@vemble.com | F64: vemble | G64: Startup/founder | H64: Radena Tsoneva (YES!Delft) | J64: AZ3WHM | K64: Free | L64: Bounce | M64: =VLOOKUP(E64,'MTS 2026 registrations'!B:B,1,false) -> #N/A | N64: =VLOOKUP(B64,'MTS 2026 registrations'!A:A,1,false) -> #N/A | O64: =IF(AND(ISNA(M64), ISNA(N64)), "Marked", "") -> Marked
A65: =B65&" "&F65 -> Joost Bouman atmosuav | B65: Joost Bouman | C65: Joost | D65: Bouman | E65: joost.bouman@atmosuav.com | F65: atmosuav | G65: Startup/founder | H65: Radena Tsoneva (YES!Delft) | J65: 7QT78C | K65: Free | L65: Bounce | M65: =VLOOKUP(E65,'MTS 2026 registrations'!B:B,1,false) -> #N/A | N65: =VLOOKUP(B65,'MTS 2026 registrations'!A:A,1,false) -> #N/A | O65: =IF(AND(ISNA(M65), ISNA(N65)), "Marked", "") -> Marked
A66: =B66&" "&F66 -> Joost Dekker ChemSIX | B66: Joost Dekker | C66: Joost | D66: Dekker | E66: Joost.dekker@chemsix.com | F66: ChemSIX | G66: Startup/founder | H66: Radena Tsoneva (YES!Delft) | J66: 8NH091 | K66: Free | L66: Bounce | M66: =VLOOKUP(E66,'MTS 2026 registrations'!B:B,1,false) -> #N/A | N66: =VLOOKUP(B66,'MTS 2026 registrations'!A:A,1,false) -> #N/A | O66: =IF(AND(ISNA(M66), ISNA(N66)), "Marked", "") -> Marked
A67: =B67&" "&F67 -> Joost Dieben maeve | B67: Joost Dieben | C67: Joost | D67: Dieben | E67: jdieben@maeve.aero | F67: maeve | G67: Startup/founder | H67: Radena Tsoneva (YES!Delft) | J67: 0CPCB0 | K67: Free | L67: Bounce | M67: =VLOOKUP(E67,'MTS 2026 registrations'!B:B,1,false) -> #N/A | N67: =VLOOKUP(B67,'MTS 2026 registrations'!A:A,1,false) -> #N/A | O67: =IF(AND(ISNA(M67), ISNA(N67)), "Marked", "") -> Marked
A68: =B68&" "&F68 -> Joost van Oorschot Synkick | B68: Joost van Oorschot | C68: Joost | D68: van Oorschot | E68: vanoorschot@synkick.com | F68: Synkick | G68: Startup/founder | H68: Radena Tsoneva (YES!Delft) | J68: 1GIR9L | K68: Free | L68: Bounce | M68: =VLOOKUP(E68,'MTS 2026 registrations'!B:B,1,false) -> #N/A | N68: =VLOOKUP(B68,'MTS 2026 registrations'!A:A,1,false) -> #N/A | O68: =IF(AND(ISNA(M68), ISNA(N68)), "Marked", "") -> Marked
A69: =B69&" "&F69 -> Jorrit Lucas Peeeks | B69: Jorrit Lucas | C69: Jorrit | D69: Lucas | E69: jorrit.lucas@peeekspower.com | F69: Peeeks | G69: Startup/founder | H69: Radena Tsoneva (YES!Delft) | J69: IZKWJV | K69: Free | L69: Bounce | M69: =VLOOKUP(E69,'MTS 2026 registrations'!B:B,1,false) -> #N/A | N69: =VLOOKUP(B69,'MTS 2026 registrations'!A:A,1,false) -> #N/A | O69: =IF(AND(ISNA(M69), ISNA(N69)), "Marked", "") -> Marked
A70: =B70&" "&F70 -> K G Smit Gensos | B70: K G Smit | C70: K G | D70: Smit | E70: k.g.smit@gensos.nl | F70: Gensos | G70: Startup/founder | H70: Radena Tsoneva (YES!Delft) | J70: C1VOQK | K70: Free | L70: Bounce | M70: =VLOOKUP(E70,'MTS 2026 registrations'!B:B,1,false) -> #N/A | N70: =VLOOKUP(B70,'MTS 2026 registrations'!A:A,1,false) -> #N/A | O70: =IF(AND(ISNA(M70), ISNA(N70)), "Marked", "") -> Marked
A71: =B71&" "&F71 -> Koen Bertels Bluebee | B71: Koen Bertels | C71: Koen | D71: Bertels | E71: k.l.m.bertels@tudelft.nl | F71: Bluebee | G71: Startup/founder | H71: Radena Tsoneva (YES!Delft) | J71: 0MVJVS | K71: Free | L71: Bounce | M71: =VLOOKUP(E71,'MTS 2026 registrations'!B:B,1,false) -> #N/A | N71: =VLOOKUP(B71,'MTS 2026 registrations'!A:A,1,false) -> #N/A | O71: =IF(AND(ISNA(M71), ISNA(N71)), "Marked", "") -> Marked
A72: =B72&" "&F72 -> Koen FlexSol Solutions | B72: Koen | C72: Koen | E72: koen@flexsolsolutions.com | F72: FlexSol Solutions | G72: Startup/founder | H72: Radena Tsoneva (YES!Delft) | J72: SAWYNX | K72: Free | L72: Bounce | M72: =VLOOKUP(E72,'MTS 2026 registrations'!B:B,1,false) -> #N/A | N72: =VLOOKUP(B72,'MTS 2026 registrations'!A:A,1,false) -> #N/A | O72: =IF(AND(ISNA(M72), ISNA(N72)), "Marked", "") -> Marked
A73: =B73&" "&F73 -> Koen van der Maaden uprax | B73: Koen van der Maaden | C73: Koen | D73: van der Maaden | E73: koen.van.der.maaden@uprax.nl | F73: uprax | G73: Startup/founder | H73: Radena Tsoneva (YES!Delft) | J73: 7XGA5N | K73: Free | L73: Bounce | M73: =VLOOKUP(E73,'MTS 2026 registrations'!B:B,1,false) -> #N/A | N73: =VLOOKUP(B73,'MTS 2026 registrations'!A:A,1,false) -> #N/A | O73: =IF(AND(ISNA(M73), ISNA(N73)), "Marked", "") -> Marked
A74: =B74&" "&F74 -> Leander Ross Type22 (QuinTech) | B74: Leander Ross | C74: Leander | D74: Ross | E74: leander@quintech.nl | F74: Type22 (QuinTech) | G74: Startup/founder | H74: Radena Tsoneva (YES!Delft) | J74: BG2L4P | K74: Free | L74: Bounce | M74: =VLOOKUP(E74,'MTS 2026 registrations'!B:B,1,false) -> #N/A | N74: =VLOOKUP(B74,'MTS 2026 registrations'!A:A,1,false) -> #N/A | O74: =IF(AND(ISNA(M74), ISNA(N74)), "Marked", "") -> Marked
A75: =B75&" "&F75 -> Lidewij van Twillert meshlingerie | B75: Lidewij van Twillert | C75: Lidewij | D75: van Twillert | E75: lidewij@meshlingerie.nl | F75: meshlingerie | G75: Startup/founder | H75: Radena Tsoneva (YES!Delft) | J75: 2NEX7G | K75: Free | L75: Bounce | M75: =VLOOKUP(E75,'MTS 2026 registrations'!B:B,1,false) -> #N/A | N75: =VLOOKUP(B75,'MTS 2026 registrations'!A:A,1,false) -> #N/A | O75: =IF(AND(ISNA(M75), ISNA(N75)), "Marked", "") -> Marked
A76: =B76&" "&F76 -> Lisanne van Dijk Crescent Technologies | B76: Lisanne van Dijk | C76: Lisanne | D76: van Dijk | E76: lisanne@crscnt.tech | F76: Crescent Technologies | G76: Startup/founder | H76: Radena Tsoneva (YES!Delft) | J76: WCS8NF | K76: Free | L76: Bounce | M76: =VLOOKUP(E76,'MTS 2026 registrations'!B:B,1,false) -> #N/A | N76: =VLOOKUP(B76,'MTS 2026 registrations'!A:A,1,false) -> #N/A | O76: =IF(AND(ISNA(M76), ISNA(N76)), "Marked", "") -> Marked
A77: =B77&" "&F77 -> M Wisse Lacquey Robot Grasping Solutions | B77: M Wisse | C77: M | D77: Wisse | E77: m.wisse@lacquey.nl | F77: Lacquey Robot Grasping Solutions | G77: Startup/founder | H77: Radena Tsoneva (YES!Delft) | J77: 9J1HMM | K77: Free | L77: Bounce | M77: =VLOOKUP(E77,'MTS 2026 registrations'!B:B,1,false) -> #N/A | N77: =VLOOKUP(B77,'MTS 2026 registrations'!A:A,1,false) -> #N/A | O77: =IF(AND(ISNA(M77), ISNA(N77)), "Marked", "") -> Marked
A78: =B78&" "&F78 -> M de meijer Nerdalize | B78: M de meijer | C78: M | D78: de meijer | E78: m.demeijer@nerdalize.com | F78: Nerdalize | G78: Startup/founder | H78: Radena Tsoneva (YES!Delft) | J78: WLW13H | K78: Free | L78: Bounce | M78: =VLOOKUP(E78,'MTS 2026 registrations'!B:B,1,false) -> #N/A | N78: =VLOOKUP(B78,'MTS 2026 registrations'!A:A,1,false) -> #N/A | O78: =IF(AND(ISNA(M78), ISNA(N78)), "Marked", "") -> Marked
A79: =B79&" "&F79 -> Maarten Kuijper deltasync | B79: Maarten Kuijper | C79: Maarten | D79: Kuijper | E79: maarten@deltasync.nl | F79: deltasync | G79: Startup/founder | H79: Radena Tsoneva (YES!Delft) | J79: JRUP5I | K79: Free | L79: Bounce | M79: =VLOOKUP(E79,'MTS 2026 registrations'!B:B,1,false) -> #N/A | N79: =VLOOKUP(B79,'MTS 2026 registrations'!A:A,1,false) -> #N/A | O79: =IF(AND(ISNA(M79), ISNA(N79)), "Marked", "") -> Marked
A80: =B80&" "&F80 -> Maayke Aimee Damen Excess Materials Exchange | B80: Maayke Aimee Damen | C80: Maayke Aimee | D80: Damen | E80: maaykedamen@excessmaterialsexchange.com | F80: Excess Materials Exchange | G80: Startup/founder | H80: Radena Tsoneva (YES!Delft) | J80: D7MEN3 | K80: Free | L80: Bounce | M80: =VLOOKUP(E80,'MTS 2026 registrations'!B:B,1,false) -> #N/A | N80: =VLOOKUP(B80,'MTS 2026 registrations'!A:A,1,false) -> #N/A | O80: =IF(AND(ISNA(M80), ISNA(N80)), "Marked", "") -> Marked
A81: =B81&" "&F81 -> Marcel Kroezen Mungosworks | B81: Marcel Kroezen | C81: Marcel | D81: Kroezen | E81: marcel@mungosworks.nl | F81: Mungosworks | G81: Startup/founder | H81: Radena Tsoneva (YES!Delft) | J81: H2HSBI | K81: Free | L81: Bounce | M81: =VLOOKUP(E81,'MTS 2026 registrations'!B:B,1,false) -> #N/A | N81: =VLOOKUP(B81,'MTS 2026 registrations'!A:A,1,false) -> #N/A | O81: =IF(AND(ISNA(M81), ISNA(N81)), "Marked", "") -> Marked
A82: =B82&" "&F82 -> Marie-jose Tekkoo | B82: Marie-jose | C82: Marie-jose | F82: Tekkoo | G82: Corporate | H82: Moshe Sijben (YES!Delft) | K82: NO | L82: Bounce | M82: =VLOOKUP(E82,'MTS 2026 registrations'!B:B,1,false) -> #N/A | N82: =VLOOKUP(B82,'MTS 2026 registrations'!A:A,1,false) -> #N/A | O82: =IF(AND(ISNA(M82), ISNA(N82)), "Marked", "") -> Marked
A83: =B83&" "&F83 -> Marije Wassenaar ams-institute.org | B83: Marije Wassenaar | C83: Marije | D83: Wassenaar | E83: marije.wassenaar@ams-institute.org | F83: ams-institute.org | G83: Partner | H83: Ras Lalmy (YES!Delft) | J83: 27MP3A | K83: Free | L83: Bounce | M83: =VLOOKUP(E83,'MTS 2026 registrations'!B:B,1,false) -> #N/A | N83: =VLOOKUP(B83,'MTS 2026 registrations'!A:A,1,false) -> #N/A | O83: =IF(AND(ISNA(M83), ISNA(N83)), "Marked", "") -> Marked
A84: =B84&" "&F84 -> Marijn Flipse Boltmobility | B84: Marijn Flipse | C84: Marijn | D84: Flipse | E84: marijnflipse@boltmobility.nl | F84: Boltmobility | G84: Startup/founder | H84: Radena Tsoneva (YES!Delft) | J84: 3YPGHZ | K84: Free | L84: Bounce | M84: =VLOOKUP(E84,'MTS 2026 registrations'!B:B,1,false) -> #N/A | N84: =VLOOKUP(B84,'MTS 2026 registrations'!A:A,1,false) -> #N/A | O84: =IF(AND(ISNA(M84), ISNA(N84)), "Marked", "") -> Marked
A85: =B85&" "&F85 -> Mark Appels ABU Engineered Solutions | B85: Mark Appels | C85: Mark | D85: Appels | E85: mark.appels@abu-es.com | F85: ABU Engineered Solutions | G85: Startup/founder | H85: Radena Tsoneva (YES!Delft) | J85: FS5SRB | K85: Free | L85: Bounce | M85: =VLOOKUP(E85,'MTS 2026 registrations'!B:B,1,false) -> #N/A | N85: =VLOOKUP(B85,'MTS 2026 registrations'!A:A,1,false) -> #N/A | O85: =IF(AND(ISNA(M85), ISNA(N85)), "Marked", "") -> Marked
A86: =B86&" "&F86 -> Martijn Vogten steljevraag | B86: Martijn Vogten | C86: Martijn | D86: Vogten | E86: martijn@steljevraag.nl | F86: steljevraag | G86: Startup/founder | H86: Radena Tsoneva (YES!Delft) | J86: K5DERX | K86: Free | L86: Bounce | M86: =VLOOKUP(E86,'MTS 2026 registrations'!B:B,1,false) -> #N/A | N86: =VLOOKUP(B86,'MTS 2026 registrations'!A:A,1,false) -> #N/A | O86: =IF(AND(ISNA(M86), ISNA(N86)), "Marked", "") -> Marked
A87: =B87&" "&F87 -> Martin van Hemert lexiq | B87: Martin van Hemert | C87: Martin | D87: van Hemert | E87: martin@lexiq.nl | F87: lexiq | G87: Startup/founder | H87: Radena Tsoneva (YES!Delft) | J87: R6AAO1 | K87: Free | L87: Bounce | M87: =VLOOKUP(E87,'MTS 2026 registrations'!B:B,1,false) -> #N/A | N87: =VLOOKUP(B87,'MTS 2026 registrations'!A:A,1,false) -> #N/A | O87: =IF(AND(ISNA(M87), ISNA(N87)), "Marked", "") -> Marked
A88: =B88&" "&F88 -> Martin prins The Datacenter Group | B88: Martin prins | C88: Martin | D88: prins | E88: martin.prins@tdcg.nl | F88: The Datacenter Group | G88: Startup/founder | H88: Radena Tsoneva (YES!Delft) | J88: FDC3KN | K88: Free | L88: Bounce | M88: =VLOOKUP(E88,'MTS 2026 registrations'!B:B,1,false) -> #N/A | N88: =VLOOKUP(B88,'MTS 2026 registrations'!A:A,1,false) -> #N/A | O88: =IF(AND(ISNA(M88), ISNA(N88)), "Marked", "") -> Marked
A89: =B89&" "&F89 -> Mels van Hoolwerff solarmonkey | B89: Mels van Hoolwerff | C89: Mels | D89: van Hoolwerff | E89: mels@solarmonkey.nl | F89: solarmonkey | G89: Startup/founder | H89: Radena Tsoneva (YES!Delft) | J89: DZR8SY | K89: Free | L89: Bounce | M89: =VLOOKUP(E89,'MTS 2026 registrations'!B:B,1,false) -> #N/A | N89: =VLOOKUP(B89,'MTS 2026 registrations'!A:A,1,false) -> #N/A | O89: =IF(AND(ISNA(M89), ISNA(N89)), "Marked", "") -> Marked
A90: =B90&" "&F90 -> Michael van der Cammen LexIQ | B90: Michael van der Cammen | C90: Michael | D90: van der Cammen | E90: michael.vandercammen@lexiq.nl | F90: LexIQ | G90: Startup/founder | H90: Radena Tsoneva (YES!Delft) | J90: OEUT4V | K90: Free | L90: Bounce | M90: =VLOOKUP(E90,'MTS 2026 registrations'!B:B,1,false) -> #N/A | N90: =VLOOKUP(B90,'MTS 2026 registrations'!A:A,1,false) -> #N/A | O90: =IF(AND(ISNA(M90), ISNA(N90)), "Marked", "") -> Marked
A91: =B91&" "&F91 -> Michael van Schie newcompliance | B91: Michael van Schie | C91: Michael | D91: van Schie | E91: mike@newcompliance.nl | F91: newcompliance | G91: Startup/founder | H91: Radena Tsoneva (YES!Delft) | J91: X908SC | K91: Free | L91: Bounce | M91: =VLOOKUP(E91,'MTS 2026 registrations'!B:B,1,false) -> #N/A | N91: =VLOOKUP(B91,'MTS 2026 registrations'!A:A,1,false) -> #N/A | O91: =IF(AND(ISNA(M91), ISNA(N91)), "Marked", "") -> Marked
A92: =B92&" "&F92 -> Michael Fritschi SpringScan | B92: Michael Fritschi | C92: Michael | D92: Fritschi | E92: m.fritschi@springscan.com | F92: SpringScan | G92: Startup/founder | H92: Radena Tsoneva (YES!Delft) | J92: 2K6X23 | K92: Free | L92: Bounce | M92: =VLOOKUP(E92,'MTS 2026 registrations'!B:B,1,false) -> #N/A | N92: =VLOOKUP(B92,'MTS 2026 registrations'!A:A,1,false) -> #N/A | O92: =IF(AND(ISNA(M92), ISNA(N92)), "Marked", "") -> Marked
A93: =B93&" "&F93 -> Michael Jenkins - JP motorcycles JP Motorcycles | B93: Michael Jenkins - JP motorcycles | C93: Michael Jenkins - JP | D93: motorcycles | E93: michael.jenkins@jpmotorcycles.nl | F93: JP Motorcycles | G93: Startup/founder | H93: Radena Tsoneva (YES!Delft) | J93: GNGXMH | K93: Free | L93: Bounce | M93: =VLOOKUP(E93,'MTS 2026 registrations'!B:B,1,false) -> #N/A | N93: =VLOOKUP(B93,'MTS 2026 registrations'!A:A,1,false) -> #N/A | O93: =IF(AND(ISNA(M93), ISNA(N93)), "Marked", "") -> Marked
A94: =B94&" "&F94 -> Murat Tarakci rsm | B94: Murat Tarakci | C94: Murat | D94: Tarakci | E94: tarakci@rsm.nl | F94: rsm | G94: Education/research | H94: Moshe Sijben (YES!Delft) | K94: NO | L94: Bounce | M94: =VLOOKUP(E94,'MTS 2026 registrations'!B:B,1,false) -> #N/A | N94: =VLOOKUP(B94,'MTS 2026 registrations'!A:A,1,false) -> #N/A | O94: =IF(AND(ISNA(M94), ISNA(N94)), "Marked", "") -> Marked
A95: =B95&" "&F95 -> Nazli Cila Tebesir | B95: Nazli Cila | C95: Nazli | D95: Cila | E95: n.cila@tudelft.com | F95: Tebesir | G95: Startup/founder | H95: Radena Tsoneva (YES!Delft) | J95: RMPB67 | K95: Free | L95: Bounce | M95: =VLOOKUP(E95,'MTS 2026 registrations'!B:B,1,false) -> #N/A | N95: =VLOOKUP(B95,'MTS 2026 registrations'!A:A,1,false) -> #N/A | O95: =IF(AND(ISNA(M95), ISNA(N95)), "Marked", "") -> Marked
A96: =B96&" "&F96 -> Nebras Ozzo conical | B96: Nebras Ozzo | C96: Nebras | D96: Ozzo | E96: nebras@conical.ai | F96: conical | G96: Startup/founder | H96: Radena Tsoneva (YES!Delft) | J96: DZZWDX | K96: Free | L96: Bounce | M96: =VLOOKUP(E96,'MTS 2026 registrations'!B:B,1,false) -> #N/A | N96: =VLOOKUP(B96,'MTS 2026 registrations'!A:A,1,false) -> #N/A | O96: =IF(AND(ISNA(M96), ISNA(N96)), "Marked", "") -> Marked
A97: =B97&" "&F97 -> Niko van Meurs olympian | B97: Niko van Meurs | C97: Niko | D97: van Meurs | E97: niko@olympian.ai | F97: olympian | G97: Startup/founder | H97: Radena Tsoneva (YES!Delft) | J97: W3KVV7 | K97: Free | L97: Bounce | M97: =VLOOKUP(E97,'MTS 2026 registrations'!B:B,1,false) -> #N/A | N97: =VLOOKUP(B97,'MTS 2026 registrations'!A:A,1,false) -> #N/A | O97: =IF(AND(ISNA(M97), ISNA(N97)), "Marked", "") -> Marked
A98: =B98&" "&F98 -> Patrick Savalle Mobbr Crowd Payment | B98: Patrick Savalle | C98: Patrick | D98: Savalle | E98: patrick@mobbr.com | F98: Mobbr Crowd Payment | G98: Startup/founder | H98: Radena Tsoneva (YES!Delft) | J98: 98WUUL | K98: Free | L98: Bounce | M98: =VLOOKUP(E98,'MTS 2026 registrations'!B:B,1,false) -> #N/A | N98: =VLOOKUP(B98,'MTS 2026 registrations'!A:A,1,false) -> #N/A | O98: =IF(AND(ISNA(M98), ISNA(N98)), "Marked", "") -> Marked
A99: =B99&" "&F99 -> Paul Breur Mungosworks | B99: Paul Breur | C99: Paul | D99: Breur | E99: Paul@mungosworks.nl | F99: Mungosworks | G99: Startup/founder | H99: Radena Tsoneva (YES!Delft) | J99: IPRK8U | K99: Free | L99: Bounce | M99: =VLOOKUP(E99,'MTS 2026 registrations'!B:B,1,false) -> #N/A | N99: =VLOOKUP(B99,'MTS 2026 registrations'!A:A,1,false) -> #N/A | O99: =IF(AND(ISNA(M99), ISNA(N99)), "Marked", "") -> Marked
A100: =B100&" "&F100 -> Peter Brouwer 4FOLD (Holland Container Innovations) | B100: Peter Brouwer | C100: Peter | D100: Brouwer | E100: p.brouwer@hcinnovations.nl | F100: 4FOLD (Holland Container Innovations) | G100: Startup/founder | H100: Radena Tsoneva (YES!Delft) | J100: OTYPOK | K100: Free | L100: Bounce | M100: =VLOOKUP(E100,'MTS 2026 registrations'!B:B,1,false) -> #N/A | N100: =VLOOKUP(B100,'MTS 2026 registrations'!A:A,1,false) -> #N/A | O100: =IF(AND(ISNA(M100), ISNA(N100)), "Marked", "") -> Marked
A101: =B101&" "&F101 -> Peter Hulshof gradyent | B101: Peter Hulshof | C101: Peter | D101: Hulshof | E101: peter@gradyent.ai | F101: gradyent | G101: Startup/founder | H101: Freek Smoes (YES!Delft) | I101: Niet meer bij Gradyent | K101: NO | L101: Bounce | M101: =VLOOKUP(E101,'MTS 2026 registrations'!B:B,1,false) -> #N/A | N101: =VLOOKUP(B101,'MTS 2026 registrations'!A:A,1,false) -> #N/A | O101: =IF(AND(ISNA(M101), ISNA(N101)), "Marked", "") -> Marked
A102: =B102&" "&F102 -> Phuc Vuong ABU Engineered Solutions | B102: Phuc Vuong | C102: Phuc | D102: Vuong | E102: phuc.vuong@abu-es.com | F102: ABU Engineered Solutions | G102: Startup/founder | H102: Radena Tsoneva (YES!Delft) | J102: J3HIW4 | K102: Free | L102: Bounce | M102: =VLOOKUP(E102,'MTS 2026 registrations'!B:B,1,false) -> #N/A | N102: =VLOOKUP(B102,'MTS 2026 registrations'!A:A,1,false) -> #N/A | O102: =IF(AND(ISNA(M102), ISNA(N102)), "Marked", "") -> Marked
A103: =B103&" "&F103 -> Pietro Faggiani kitepower | B103: Pietro Faggiani | C103: Pietro | D103: Faggiani | E103: p.faggiani@kitepower.nl | F103: kitepower | G103: Startup/founder | H103: Radena Tsoneva (YES!Delft) | J103: KWURHT | K103: Free | L103: Bounce | M103: =VLOOKUP(E103,'MTS 2026 registrations'!B:B,1,false) -> #N/A | N103: =VLOOKUP(B103,'MTS 2026 registrations'!A:A,1,false) -> #N/A | O103: =IF(AND(ISNA(M103), ISNA(N103)), "Marked", "") -> Marked
A104: =B104&" "&F104 -> Pinhas Reich ForceSense (Medishield) | B104: Pinhas Reich | C104: Pinhas | D104: Reich | E104: pinhas@voicesense.com | F104: ForceSense (Medishield) | G104: Startup/founder | H104: Radena Tsoneva (YES!Delft) | J104: JWSSKX | K104: Free | L104: Bounce | M104: =VLOOKUP(E104,'MTS 2026 registrations'!B:B,1,false) -> #N/A | N104: =VLOOKUP(B104,'MTS 2026 registrations'!A:A,1,false) -> #N/A | O104: =IF(AND(ISNA(M104), ISNA(N104)), "Marked", "") -> Marked
A105: =B105&" "&F105 -> Pradeep Pandurangi Levitas Composite Structures | B105: Pradeep Pandurangi | C105: Pradeep | D105: Pandurangi | E105: pradeep@levitascomposites.com | F105: Levitas Composite Structures | G105: Startup/founder | H105: Radena Tsoneva (YES!Delft) | J105: D051DR | K105: Free | L105: Bounce | M105: =VLOOKUP(E105,'MTS 2026 registrations'!B:B,1,false) -> #N/A | N105: =VLOOKUP(B105,'MTS 2026 registrations'!A:A,1,false) -> #N/A | O105: =IF(AND(ISNA(M105), ISNA(N105)), "Marked", "") -> Marked
A106: =B106&" "&F106 -> R Blokker Bluerise | B106: R Blokker | C106: R | D106: Blokker | E106: r.blokker@bluerise.nl | F106: Bluerise | G106: Startup/founder | H106: Radena Tsoneva (YES!Delft) | J106: 54YUHJ | K106: Free | L106: Bounce | M106: =VLOOKUP(E106,'MTS 2026 registrations'!B:B,1,false) -> #N/A | N106: =VLOOKUP(B106,'MTS 2026 registrations'!A:A,1,false) -> #N/A | O106: =IF(AND(ISNA(M106), ISNA(N106)), "Marked", "") -> Marked
A107: =B107&" "&F107 -> Rafael Carvalho RiskApp | B107: Rafael Carvalho | C107: Rafael | D107: Carvalho | E107: rafael@riskapp.com | F107: RiskApp | G107: Startup/founder | H107: Radena Tsoneva (YES!Delft) | J107: YVYMXD | K107: Free | L107: Bounce | M107: =VLOOKUP(E107,'MTS 2026 registrations'!B:B,1,false) -> #N/A | N107: =VLOOKUP(B107,'MTS 2026 registrations'!A:A,1,false) -> #N/A | O107: =IF(AND(ISNA(M107), ISNA(N107)), "Marked", "") -> Marked
A108: =B108&" "&F108 -> Raimond Haan arnold-siedsma | B108: Raimond Haan | C108: Raimond | D108: Haan | E108: rhaan@arnold-siedsma.nl | F108: arnold-siedsma | G108: Partner | H108: Radena Tsoneva (YES!Delft) | J108: 0M5VJL | K108: Free | L108: Bounce | M108: =VLOOKUP(E108,'MTS 2026 registrations'!B:B,1,false) -> #N/A | N108: =VLOOKUP(B108,'MTS 2026 registrations'!A:A,1,false) -> #N/A | O108: =IF(AND(ISNA(M108), ISNA(N108)), "Marked", "") -> Marked
A109: =B109&" "&F109 -> Ranjeet Sengar Yokai | B109: Ranjeet Sengar | C109: Ranjeet | D109: Sengar | E109: ranjeet@yokai.network | F109: Yokai | G109: Startup/founder | H109: Radena Tsoneva (YES!Delft) | J109: ESXFJC | K109: Free | L109: Bounce | M109: =VLOOKUP(E109,'MTS 2026 registrations'!B:B,1,false) -> #N/A | N109: =VLOOKUP(B109,'MTS 2026 registrations'!A:A,1,false) -> #N/A | O109: =IF(AND(ISNA(M109), ISNA(N109)), "Marked", "") -> Marked
A110: =B110&" "&F110 -> Rik van den Reijen CO2Zero | B110: Rik van den Reijen | C110: Rik | D110: van den Reijen | E110: Rik@CO2Zero.online | F110: CO2Zero | G110: Startup/founder | H110: Radena Tsoneva (YES!Delft) | J110: ZGQGT2 | K110: Free | L110: Bounce | M110: =VLOOKUP(E110,'MTS 2026 registrations'!B:B,1,false) -> #N/A | N110: =VLOOKUP(B110,'MTS 2026 registrations'!A:A,1,false) -> #N/A | O110: =IF(AND(ISNA(M110), ISNA(N110)), "Marked", "") -> Marked
...

Sheet removed contacts
A1: Name+ company | B1: Name | C1: Name1 | D1: Name 2 | E1: mail | F1: company | G1: type | H1: connection | J1: Registered | K1: Invite | L1: Email 4 sent? | M1: Script check? | N1: Notes:
A2: =B2&" "&F2 -> Dieuwke Hoogland Female Ventures | B2: =C2&" "&D2 -> Dieuwke Hoogland | C2: Dieuwke | D2: Hoogland | E2: dieuwke@femaleventures.nl | F2: Female Ventures | G2: Startup Ecosystem | H2: Pablo Benéitez (YES!Delft) | K2: NO | L2: x | M2: NIET | O2: =vlookup(E2,Sheet16!B:C,1,false) -> #REF!
A3: =B3&" "&F3 -> Vera Hunter eur | B3: =C3&" "&D3 -> Vera Hunter | C3: Vera | D3: Hunter | E3: vera.hunter@eur.nl | F3: eur | G3: Education/research | H3: Moshe Sijben (YES!Delft) | J3: FALSE | K3: other job | L3: x | M3: Registered | O3: =vlookup(E3,Sheet16!B:C,1,false) -> #REF!
A4: =B4&" "&F4 -> Adrie Huesman shell | B4: =C4&" "&D4 -> Adrie Huesman | C4: Adrie | D4: Huesman | E4: adrie.huesman@shell.com | F4: shell | G4: Corporate | H4: Nannila Zevenhuizen (YES!Delft) | K4: NO | L4: NO | M4: NIET | O4: =vlookup(E4,Sheet16!B:C,1,false) -> #REF!
A5: =B5&" "&F5 -> Alkis Romeos shell | B5: =C5&" "&D5 -> Alkis Romeos | C5: Alkis | D5: Romeos | E5: alkis.romeos@shell.com | F5: shell | G5: Corporate | H5: Nannila Zevenhuizen (YES!Delft) | K5: NO | L5: NO | M5: NIET | O5: =vlookup(E5,Sheet16!B:C,1,false) -> #REF!
A6: =B6&" "&F6 -> Carola Berkouwer Rabobank | B6: =C6&" "&D6 -> Carola Berkouwer | C6: Carola | D6: Berkouwer | E6: Carola.Berkouwer@rabobank.nl | F6: Rabobank | G6: Partner | H6: Nannila Zevenhuizen (YES!Delft) | K6: NO | L6: NO | M6: Sent to Carola.Berkouwer@rabobank.nl on 2025-09-01 | O6: =vlookup(E6,Sheet16!B:C,1,false) -> #REF!
A7: =B7&" "&F7 -> Claire Rutteman Shell | B7: =C7&" "&D7 -> Claire Rutteman | C7: Claire | D7: Rutteman | E7: Claire.Rutteman@shell.com | F7: Shell | G7: Corporate | H7: Nannila Zevenhuizen (YES!Delft) | K7: NO | L7: NO | M7: Registered | O7: =vlookup(E7,Sheet16!B:C,1,false) -> #REF!
A8: =B8&" "&F8 -> Geert van de Wouw shell | B8: =C8&" "&D8 -> Geert van de Wouw | C8: Geert | D8: van de Wouw | E8: geert.vandewouw@shell.com | F8: shell | G8: Corporate | H8: Nannila Zevenhuizen (YES!Delft) | K8: NO | L8: NO | M8: NIET | O8: =vlookup(E8,Sheet16!B:C,1,false) -> #REF!
A9: =B9&" "&F9 -> Jaap Hulshoff duravermeer | B9: =C9&" "&D9 -> Jaap Hulshoff | C9: Jaap | D9: Hulshoff | E9: j.hulshoff@duravermeer.nl | F9: duravermeer | G9: Corporate | H9: Nannila Zevenhuizen (YES!Delft) | K9: NO | L9: NO | M9: Sent to j.hulshoff@duravermeer.nl on 2025-09-01 | O9: =vlookup(E9,Sheet16!B:C,1,false) -> #REF!
A10: =B10&" "&F10 -> Kiki de Vries yesdelftstudents | B10: =C10&" "&D10 -> Kiki de Vries | C10: Kiki | D10: de Vries | E10: kiki@yesdelftstudents.nl | F10: yesdelftstudents | G10: Startup Ecosystem | H10: Nannila Zevenhuizen (YES!Delft) | K10: NO | L10: NO | M10: NIET | O10: =vlookup(E10,Sheet16!B:C,1,false) -> #REF!
A11: =B11&" "&F11 -> Marcin Dukalski aramcooverseas | B11: =C11&" "&D11 -> Marcin Dukalski | C11: Marcin | D11: Dukalski | E11: marcin.dukalski@aramcooverseas.com | F11: aramcooverseas | G11: Partner | H11: Nannila Zevenhuizen (YES!Delft) | K11: NO | L11: NO | M11: NIET | O11: =vlookup(E11,Sheet16!B:C,1,false) -> #REF!
A12: =B12&" "&F12 -> Sayee Balaji shell | B12: =C12&" "&D12 -> Sayee Balaji | C12: Sayee | D12: Balaji | E12: sayee-prasaad.balaji@shell.com | F12: shell | G12: Corporate | H12: Nannila Zevenhuizen (YES!Delft) | K12: NO | L12: NO | M12: NIET | O12: =vlookup(E12,Sheet16!B:C,1,false) -> #REF!
A13: =B13&" "&F13 -> Sylvia Coenen Gemeente Delft | B13: =C13&" "&D13 -> Sylvia Coenen | C13: Sylvia | D13: Coenen | E13: scoenen@delft.nl | F13: Gemeente Delft | G13: Startup Ecosystem | H13: Nannila Zevenhuizen (YES!Delft) | K13: NO | L13: NO | M13: NIET | O13: =vlookup(E13,Sheet16!B:C,1,false) -> #REF!
A14: =B14&" "&F14 -> Unsal Evren shell | B14: =C14&" "&D14 -> Unsal Evren | C14: Unsal | D14: Evren | E14: evren.unsal@shell.com | F14: shell | G14: Corporate | H14: Nannila Zevenhuizen (YES!Delft) | K14: NO | L14: NO | M14: NIET | O14: =vlookup(E14,Sheet16!B:C,1,false) -> #REF!
A15: =B15&" "&F15 -> Wim Nobel rabobank | B15: =C15&" "&D15 -> Wim Nobel | C15: Wim | D15: Nobel | E15: wim.nobel@rabobank.nl | F15: rabobank | G15: Partner | H15: Ras Lalmy (YES!Delft) | J15: FALSE | K15: yes | L15: x | M15: NIET | O15: =vlookup(E15,Sheet16!B:C,1,false) -> #REF!
A16: =B16&" "&F16 -> Raf Koene innovationquarter | B16: =C16&" "&D16 -> Raf Koene | C16: Raf | D16: Koene | F16: innovationquarter | G16: Investor | H16: Jan Geert van Hall (YES!Delft) | K16: NO | L16: NO | M16: Does not work at IQ anymore | O16: =vlookup(E16,Sheet16!B:C,1,false) -> #REF!
A17: =B17&" "&F17 -> Jenny Konings tudelft | B17: =C17&" "&D17 -> Jenny Konings | C17: Jenny | D17: Konings | E17: j.j.m.konings@tudelft.nl | F17: tudelft | G17: Education/research | H17: Ras Lalmy (YES!Delft) | I17: Radena | K17: NO | L17: NO | M17: Sent to j.j.m.konings@tudelft.nl on 2025-09-01 | O17: =vlookup(E17,Sheet16!B:C,1,false) -> #REF!
A18: =B18&" "&F18 -> Zwanet van Lubek AMS Institute | B18: =C18&" "&D18 -> Zwanet van Lubek | C18: Zwanet | D18: van Lubek | F18: AMS Institute | G18: Education/research | H18: Freek Smoes (YES!Delft) | J18: FALSE | K18: NO | L18: NO
A19: =B19&" "&F19 -> Hanna Lucas innovationquarter | B19: =C19&" "&D19 -> Hanna Lucas | C19: Hanna | D19: Lucas | E19: hanna.lucas@innovationquarter.nl | F19: innovationquarter | G19: Mentor/Expert | H19: Radena Tsoneva (YES!Delft) | J19: FALSE | L19: Bounce
A20: =B20&" "&F20 -> Nathal van Rijn | B20: =C20&" "&D20 -> Nathal van Rijn | C20: Nathal | D20: van Rijn | G20: Startup Ecosystem | H20: Freek Smoes (YES!Delft) | K20: NO | L20: NO
A21: =B21&" "&F21 -> Maarten Cleeren | B21: =C21&" "&D21 -> Maarten Cleeren | C21: Maarten | D21: Cleeren | G21: Partner | H21: Ras Lalmy (YES!Delft) | J21: FALSE | K21: NO | L21: NO
A22: =B22&" "&F22 -> Sophie Heijenberg nosuchventures | B22: =C22&" "&D22 -> Sophie Heijenberg | C22: Sophie | D22: Heijenberg | F22: nosuchventures | G22: Investor | H22: Jan Geert van Hall (YES!Delft) | J22: FALSE | K22: YES
A23: =B23&" "&F23 -> Fabian van der Horst rabobank | B23: =C23&" "&D23 -> Fabian van der Horst | C23: Fabian | D23: van der Horst | E23: fabian.van.der.horst@rabobank.nl | F23: rabobank | G23: Partner | H23: Ras Lalmy (YES!Delft) | J23: FALSE | K23: Free | L23: Sent to fabian.van.der.horst@rabobank.nl on 2026-06-08 | N23: No longer Rabo
A24: =B24&" "&F24 -> Pascal van de Poll strategiemakers | B24: Pascal van de Poll | C24: Pascal | D24: van de Poll | E24: pascal.vandepoll@strategiemakers.nl | F24: strategiemakers | G24: Startup Ecosystem | I24: mentor | K24: no | L24: Bounce
A25: =B25&" "&F25 -> Serge Santoo thegreenvillage | B25: Serge Santoo | C25: Serge | D25: Santoo | E25: serge.santoo@thegreenvillage.org | F25: thegreenvillage | G25: Startup Ecosystem | I25: expert | K25: no | L25: Bounce
A27: =B27&" "&F27 -> boers | C27: Ward | D27: Bingley | E27: ward.bingley@boers.nl | F27: boers | G27: Partner | I27: expert | K27: ? | L27: NO
A28: =B28&" "&F28 -> Dilis Biesheuvel designsolutions | B28: Dilis Biesheuvel | C28: Dilis | D28: Biesheuvel | E28: dbiesheuvel@designsolutions.nl | F28: designsolutions | G28: Partner | I28: Old partner | K28: ? | L28: NO
A29: =B29&" "&F29 -> Merel Haverhals nen | B29: Merel Haverhals | C29: Merel | D29: Haverhals | E29: merel.haverhals@nen.nl | F29: nen | G29: Partner | K29: ? | L29: NO
A30: =B30&" "&F30 -> Chynna Falandt Rabobank | B30: Chynna Falandt | C30: Chynna | D30: Falandt | E30: Chynna.Falandt@rabobank.nl | F30: Rabobank | G30: Partner | K30: ? | L30: NO
A33: =B33&" "&F33 -> Alessandro Bozzon tudelft | B33: Alessandro Bozzon | C33: Alessandro | D33: Bozzon | E33: a.bozzon@tudelft.nl | F33: tudelft | G33: Education/research | I33: Ailixr? | K33: ? | L33: NO
A34: =B34&" "&F34 -> Ellen van Andel tudelft | B34: Ellen van Andel | C34: Ellen | D34: van Andel | E34: e.vanandel@tudelft.nl | F34: tudelft | G34: Education/research | K34: ? | L34: NO
A35: =B35&" "&F35 -> Hanieh Khodaei tudelft | B35: Hanieh Khodaei | C35: Hanieh | D35: Khodaei | E35: h.khodaei@tudelft.nl | F35: tudelft | G35: Education/research | K35: ? | L35: NO
A36: =B36&" "&F36 -> Jens Kok tudelft | B36: Jens Kok | C36: Jens | D36: Kok | E36: j.kok@tudelft.nl | F36: tudelft | G36: Education/research | K36: ? | L36: NO
A37: =B37&" "&F37 -> Daniel de Raadt vlst | B37: Daniel de Raadt | C37: Daniel | D37: de Raadt | E37: d.deraat@vlst.com | F37: vlst | G37: Partner | K37: ? | L37: NO
A38: =B38&" "&F38 -> Anastasia Bhadai Rabobank | B38: Anastasia Bhadai | C38: Anastasia | D38: Bhadai | E38: anastasia.bhadai@rabobank.nl | F38: Rabobank | G38: Partner | H38: Ras Lalmy (YES!Delft) | I38: x | K38: ? | L38: Sent to anastasia.bhadai@rabobank.nl on 2026-06-08
A39: =B39&" "&F39 -> Danny Winkel Rabobank | B39: Danny Winkel | C39: Danny | D39: Winkel | E39: danny.winkel@rabobank.nl | F39: Rabobank | G39: Partner | H39: Ras Lalmy (YES!Delft) | I39: x | K39: ? | L39: Sent to danny.winkel@rabobank.nl on 2026-06-08
A40: =B40&" "&F40 -> Evelien De Kort Rabobank | B40: Evelien De Kort | C40: Evelien | D40: De Kort | E40: Evelien.de.kort@rabobank.nl | F40: Rabobank | G40: Partner | H40: Ras Lalmy (YES!Delft) | K40: ? | L40: Sent to Evelien.de.kort@rabobank.nl on 2026-06-08
A41: =B41&" "&F41 -> Marius Hovius Rabobank | B41: Marius Hovius | C41: Marius | D41: Hovius | E41: marius.hovius@rabobank.nl | F41: Rabobank | G41: Partner | H41: Ras Lalmy (YES!Delft) | I41: x | K41: ? | L41: Sent to marius.hovius@rabobank.nl on 2026-06-08
A42: =B42&" "&F42 -> Patrick Van Der Toorn Rabobank | B42: Patrick Van Der Toorn | C42: Patrick | D42: Van Der Toorn | E42: patrick.van.der.toorn@rabobank.nl | F42: Rabobank | G42: Partner | H42: Ras Lalmy (YES!Delft) | K42: ? | L42: Sent to patrick.van.der.toorn@rabobank.nl on 2026-06-08
A43: =B43&" "&F43 -> Peter Smid rabobank | B43: Peter Smid | C43: Peter | D43: Smit | E43: peter.smit@rabobank.com | F43: rabobank | G43: Partner | H43: Ras Lalmy (YES!Delft) | K43: ? | L43: Sent to peter.smit@rabobank.com on 2026-06-08
A44: =B44&" "&F44 -> Rodney Goijer Rabobank | B44: Rodney Goijer | C44: Rodney | D44: Goijer | E44: rodney.goijer@rabobank.nl | F44: Rabobank | G44: Partner | H44: Ras Lalmy (YES!Delft) | I44: x | K44: ? | L44: Sent to rodney.goijer@rabobank.nl on 2026-06-08
A46: =B46&" "&F46 -> Erik Heer nl | B46: Erik Heer | C46: Erik | D46: Heer | E46: erik.de.heer@nl.ey.com | F46: nl | G46: Partner | H46: Moshe Sijben (YES!Delft) | L46: Don't send | M46: new job
A47: =B47&" "&F47 -> Maaike terwindt google | B47: Maaike terwindt | C47: Maaike | D47: terwindt | E47: terwindt@google.com | F47: google | G47: Partner | H47: Moshe Sijben (YES!Delft) | L47: Don't send | M47: new role
A48: =B48&" "&F48 -> Dirk van Lammeren primevision | B48: Dirk van Lammeren | C48: Dirk | D48: van Lammeren | F48: primevision | G48: Corporate | H48: Freek Smoes (YES!Delft) | K48: NO | L48: Bounce | M48: no primevision
A49: =B49&" "&F49 -> Michael minbuza | B49: Michael | C49: Michael | F49: minbuza | G49: Government | H49: Moshe Sijben (YES!Delft) | K49: Discount | L49: Bounce
A50: =B50&" "&F50 -> Marisa Schneider | B50: Marisa Schneider | C50: Marisa | D50: Schneider | H50: Freek Smoes (YES!Delft) | K50: Free | L50: Bounce
A51: Jolanda van Schaick pzh Jolanda van Schaick Jolanda van Schaick jm.van.schaick@pzh.nl pzh Government Freek Smoes (YES!Delft) J9J6AO Free Bounce July #N/A

Sheet MTS 2026 registrations
A1: !Data from this sheet is loaded from Project Master Sheet - MTS 2026! Registrations, DON'T EDIT THIS SHEET! | K1: =COUNTIF(K2:K500, "Marked") -> 90 | L1: Things changed in the registration sheet in MTS document so this is all fucked up now.
A2: =IFERROR(__xludf.DUMMYFUNCTION("importrange(""https://docs.google.com/spreadsheets/d/1tdVMyaSX1NOOnhLoywkFFXAlzGwYRUtaHrBX8He56SI/edit?gid=1911872096#gid=1911872096"",""Registrations!A:F"")"),"Name") -> Name | B2: =IFERROR(__xludf.DUMMYFUNCTION("""COMPUTED_VALUE"""),"Email") -> Email | C2: =IFERROR(__xludf.DUMMYFUNCTION("""COMPUTED_VALUE"""),"Company/University") -> Company/University | D2: =IFERROR(__xludf.DUMMYFUNCTION("""COMPUTED_VALUE"""),"Job title/Study") -> Job title/Study | E2: =IFERROR(__xludf.DUMMYFUNCTION("""COMPUTED_VALUE"""),"Goal of event") -> Goal of event | F2: =IFERROR(__xludf.DUMMYFUNCTION("""COMPUTED_VALUE"""),"Sectors of interest") -> Sectors of interest | G2: Used Code | H2: lookup email | I2: lookupmail | J2: Lookup used code | K2: not on our list | L2: remark
A3: =IFERROR(__xludf.DUMMYFUNCTION("""COMPUTED_VALUE"""),"Anton Schreuders") -> Anton Schreuders | B3: =IFERROR(__xludf.DUMMYFUNCTION("""COMPUTED_VALUE"""),"anton.schreuders@eao.com") -> anton.schreuders@eao.com | C3: =IFERROR(__xludf.DUMMYFUNCTION("""COMPUTED_VALUE"""),"EAO Benelux B.V.") -> EAO Benelux B.V. | D3: =IFERROR(__xludf.DUMMYFUNCTION("""COMPUTED_VALUE"""),"Applicatio Specialist machinery & ships") -> Applicatio Specialist machinery & ships | E3: =IFERROR(__xludf.DUMMYFUNCTION("""COMPUTED_VALUE"""),"new contacts") -> new contacts | F3: =IFERROR(__xludf.DUMMYFUNCTION("""COMPUTED_VALUE"""),"Maritime") -> Maritime | H3: =VLOOKUP(B3,'new total list'!E:E,1,false) -> #N/A | I3: =vlookup(A3,'new total list'!B:B,1,false) -> #N/A | K3: =IF(AND(ISNA(H3), ISNA(I3)), "Marked", "") -> Marked
A4: =IFERROR(__xludf.DUMMYFUNCTION("""COMPUTED_VALUE"""),"Paul Hendrikx") -> Paul Hendrikx | B4: =IFERROR(__xludf.DUMMYFUNCTION("""COMPUTED_VALUE"""),"paul@mangoproductdesign.com") -> paul@mangoproductdesign.com | C4: =IFERROR(__xludf.DUMMYFUNCTION("""COMPUTED_VALUE"""),"ManGo Product Design") -> ManGo Product Design | D4: =IFERROR(__xludf.DUMMYFUNCTION("""COMPUTED_VALUE"""),"CEO") -> CEO | E4: =IFERROR(__xludf.DUMMYFUNCTION("""COMPUTED_VALUE"""),"Meet the innovators of tomorrow") -> Meet the innovators of tomorrow | F4: =IFERROR(__xludf.DUMMYFUNCTION("""COMPUTED_VALUE"""),"Energy") -> Energy | H4: =VLOOKUP(B4,'new total list'!E:E,1,false) -> #N/A | I4: =vlookup(A4,'new total list'!B:B,1,false) -> #N/A | K4: =IF(AND(ISNA(H4), ISNA(I4)), "Marked", "") -> Marked
A5: =IFERROR(__xludf.DUMMYFUNCTION("""COMPUTED_VALUE"""),"Joris Roozen") -> Joris Roozen | B5: =IFERROR(__xludf.DUMMYFUNCTION("""COMPUTED_VALUE"""),"joris@jorisroozen.nl") -> joris@jorisroozen.nl | C5: =IFERROR(__xludf.DUMMYFUNCTION("""COMPUTED_VALUE"""),"Intenza Consulting & Training") -> Intenza Consulting & Training | D5: =IFERROR(__xludf.DUMMYFUNCTION("""COMPUTED_VALUE"""),"Partner") -> Partner | E5: =IFERROR(__xludf.DUMMYFUNCTION("""COMPUTED_VALUE"""),"Inspiration & Networking") -> Inspiration & Networking | F5: =IFERROR(__xludf.DUMMYFUNCTION("""COMPUTED_VALUE"""),"Energy") -> Energy | H5: =VLOOKUP(B5,'new total list'!E:E,1,false) -> #N/A | I5: =vlookup(A5,'new total list'!B:B,1,false) -> #N/A | K5: =IF(AND(ISNA(H5), ISNA(I5)), "Marked", "") -> Marked | L5: Contact Ras - potential mentor
A6: =IFERROR(__xludf.DUMMYFUNCTION("""COMPUTED_VALUE"""),"Teake Bulstra") -> Teake Bulstra | B6: =IFERROR(__xludf.DUMMYFUNCTION("""COMPUTED_VALUE"""),"teake@baatmedical.com") -> teake@baatmedical.com | C6: =IFERROR(__xludf.DUMMYFUNCTION("""COMPUTED_VALUE"""),"www.baatmedical.com") -> www.baatmedical.com | D6: =IFERROR(__xludf.DUMMYFUNCTION("""COMPUTED_VALUE"""),"new business development") -> new business development | E6: =IFERROR(__xludf.DUMMYFUNCTION("""COMPUTED_VALUE"""),"meet innovators; add value with our knowledge and experience on medical device development") -> meet innovators; add value with our knowledge and experience on medical device development | F6: =IFERROR(__xludf.DUMMYFUNCTION("""COMPUTED_VALUE"""),"manufacturing") -> manufacturing | H6: =VLOOKUP(B6,'new total list'!E:E,1,false) -> #N/A | I6: =vlookup(A6,'new total list'!B:B,1,false) -> #N/A | K6: =IF(AND(ISNA(H6), ISNA(I6)), "Marked", "") -> Marked
A7: =IFERROR(__xludf.DUMMYFUNCTION("""COMPUTED_VALUE"""),"Boudewijn Soetens") -> Boudewijn Soetens | B7: =IFERROR(__xludf.DUMMYFUNCTION("""COMPUTED_VALUE"""),"boudewijn@tekkoo.nl") -> boudewijn@tekkoo.nl | C7: =IFERROR(__xludf.DUMMYFUNCTION("""COMPUTED_VALUE"""),"Tekkoo") -> Tekkoo | D7: =IFERROR(__xludf.DUMMYFUNCTION("""COMPUTED_VALUE"""),"Senior Innovation Lead") -> Senior Innovation Lead | E7: =IFERROR(__xludf.DUMMYFUNCTION("""COMPUTED_VALUE"""),"Get to know the YesDelft ecosystem better") -> Get to know the YesDelft ecosystem better | F7: =IFERROR(__xludf.DUMMYFUNCTION("""COMPUTED_VALUE"""),"we are facilitating the BlueCity Startup Studio in Rotterdam and there is a potential to work together.") -> we are facilitating the BlueCity Startup Studio in Rotterdam and there is a potential to work together. | H7: =VLOOKUP(B7,'new total list'!E:E,1,false) -> #N/A | I7: =vlookup(A7,'new total list'!B:B,1,false) -> #N/A | K7: =IF(AND(ISNA(H7), ISNA(I7)), "Marked", "") -> Marked
A8: =IFERROR(__xludf.DUMMYFUNCTION("""COMPUTED_VALUE"""),"Katharina") -> Katharina | B8: =IFERROR(__xludf.DUMMYFUNCTION("""COMPUTED_VALUE"""),"katharina.pavlin@catalyze-group.com") -> katharina.pavlin@catalyze-group.com | C8: =IFERROR(__xludf.DUMMYFUNCTION("""COMPUTED_VALUE"""),"Catalyze BV") -> Catalyze BV | D8: =IFERROR(__xludf.DUMMYFUNCTION("""COMPUTED_VALUE"""),"Business Developer") -> Business Developer | E8: =IFERROR(__xludf.DUMMYFUNCTION("""COMPUTED_VALUE"""),"connect with startups and advice them about funding opportunities") -> connect with startups and advice them about funding opportunities | F8: =IFERROR(__xludf.DUMMYFUNCTION("""COMPUTED_VALUE"""),"Energy") -> Energy | H8: =VLOOKUP(B8,'new total list'!E:E,1,false) -> #N/A | I8: =vlookup(A8,'new total list'!B:B,1,false) -> #N/A | K8: =IF(AND(ISNA(H8), ISNA(I8)), "Marked", "") -> Marked
A9: =IFERROR(__xludf.DUMMYFUNCTION("""COMPUTED_VALUE"""),"Dymphy") -> Dymphy | B9: =IFERROR(__xludf.DUMMYFUNCTION("""COMPUTED_VALUE"""),"dymphy@baatmedical.com") -> dymphy@baatmedical.com | C9: =IFERROR(__xludf.DUMMYFUNCTION("""COMPUTED_VALUE"""),"BAAT Medical") -> BAAT Medical | D9: =IFERROR(__xludf.DUMMYFUNCTION("""COMPUTED_VALUE"""),"Business Developer") -> Business Developer | E9: =IFERROR(__xludf.DUMMYFUNCTION("""COMPUTED_VALUE"""),"Strengthen network") -> Strengthen network | F9: =IFERROR(__xludf.DUMMYFUNCTION("""COMPUTED_VALUE"""),"MedTech") -> MedTech | H9: =VLOOKUP(B9,'new total list'!E:E,1,false) -> #N/A | I9: =vlookup(A9,'new total list'!B:B,1,false) -> #N/A | K9: =IF(AND(ISNA(H9), ISNA(I9)), "Marked", "") -> Marked
A10: =IFERROR(__xludf.DUMMYFUNCTION("""COMPUTED_VALUE"""),"Jan Willem ten Dam") -> Jan Willem ten Dam | B10: =IFERROR(__xludf.DUMMYFUNCTION("""COMPUTED_VALUE"""),"j.tendam@aomb.nl") -> j.tendam@aomb.nl | C10: =IFERROR(__xludf.DUMMYFUNCTION("""COMPUTED_VALUE"""),"AOMB") -> AOMB | D10: =IFERROR(__xludf.DUMMYFUNCTION("""COMPUTED_VALUE"""),"patent attorney") -> patent attorney | E10: =IFERROR(__xludf.DUMMYFUNCTION("""COMPUTED_VALUE"""),"As an Industrial Design Engineering alumnus with friends active in YES!Delft startups") -> As an Industrial Design Engineering alumnus with friends active in YES!Delft startups | F10: =IFERROR(__xludf.DUMMYFUNCTION("""COMPUTED_VALUE"""),"I want to catch up on what happens at YES!Delft and network with new startups.") -> I want to catch up on what happens at YES!Delft and network with new startups. | H10: =VLOOKUP(B10,'new total list'!E:E,1,false) -> #N/A | I10: =vlookup(A10,'new total list'!B:B,1,false) -> #N/A | K10: =IF(AND(ISNA(H10), ISNA(I10)), "Marked", "") -> Marked
A11: =IFERROR(__xludf.DUMMYFUNCTION("""COMPUTED_VALUE"""),"Anita Lieverdink") -> Anita Lieverdink | B11: =IFERROR(__xludf.DUMMYFUNCTION("""COMPUTED_VALUE"""),"anita.lieverdink@aic4nl.nl") -> anita.lieverdink@aic4nl.nl | C11: =IFERROR(__xludf.DUMMYFUNCTION("""COMPUTED_VALUE"""),"AIC4NL") -> AIC4NL | D11: =IFERROR(__xludf.DUMMYFUNCTION("""COMPUTED_VALUE"""),"Lead AI scale-up program") -> Lead AI scale-up program | E11: =IFERROR(__xludf.DUMMYFUNCTION("""COMPUTED_VALUE"""),"scouting AI startups") -> scouting AI startups | F11: =IFERROR(__xludf.DUMMYFUNCTION("""COMPUTED_VALUE"""),"Energy") -> Energy | H11: =VLOOKUP(B11,'new total list'!E:E,1,false) -> anita.lieverdink@aic4nl.nl | I11: =vlookup(A11,'new total list'!B:B,1,false) -> Anita Lieverdink | K11: =IF(AND(ISNA(H11), ISNA(I11)), "Marked", "")
A12: =IFERROR(__xludf.DUMMYFUNCTION("""COMPUTED_VALUE"""),"Bob") -> Bob | B12: =IFERROR(__xludf.DUMMYFUNCTION("""COMPUTED_VALUE"""),"b.stassar@benedictpeax.com") -> b.stassar@benedictpeax.com | C12: =IFERROR(__xludf.DUMMYFUNCTION("""COMPUTED_VALUE"""),"Benedict Peax") -> Benedict Peax | D12: =IFERROR(__xludf.DUMMYFUNCTION("""COMPUTED_VALUE"""),"Directeur") -> Directeur | E12: =IFERROR(__xludf.DUMMYFUNCTION("""COMPUTED_VALUE"""),"Contacts") -> Contacts | F12: =IFERROR(__xludf.DUMMYFUNCTION("""COMPUTED_VALUE"""),"leads") -> leads | H12: =VLOOKUP(B12,'new total list'!E:E,1,false) -> b.stassar@benedictpeax.com | I12: =vlookup(A12,'new total list'!B:B,1,false) -> #N/A | K12: =IF(AND(ISNA(H12), ISNA(I12)), "Marked", "")
A13: =IFERROR(__xludf.DUMMYFUNCTION("""COMPUTED_VALUE"""),"Bram") -> Bram | B13: =IFERROR(__xludf.DUMMYFUNCTION("""COMPUTED_VALUE"""),"am.spitzer@pzh.nl") -> am.spitzer@pzh.nl | C13: =IFERROR(__xludf.DUMMYFUNCTION("""COMPUTED_VALUE"""),"Founded in South Holland") -> Founded in South Holland | D13: =IFERROR(__xludf.DUMMYFUNCTION("""COMPUTED_VALUE"""),"Public Lead") -> Public Lead | E13: =IFERROR(__xludf.DUMMYFUNCTION("""COMPUTED_VALUE"""),"Network") -> Network | F13: =IFERROR(__xludf.DUMMYFUNCTION("""COMPUTED_VALUE"""),"Energy") -> Energy | H13: =VLOOKUP(B13,'new total list'!E:E,1,false) -> am.spitzer@pzh.nl | I13: =vlookup(A13,'new total list'!B:B,1,false) -> #N/A | K13: =IF(AND(ISNA(H13), ISNA(I13)), "Marked", "")
A14: =IFERROR(__xludf.DUMMYFUNCTION("""COMPUTED_VALUE"""),"Freek Smoes") -> Freek Smoes | B14: =IFERROR(__xludf.DUMMYFUNCTION("""COMPUTED_VALUE"""),"freek@yesdelft.nl") -> freek@yesdelft.nl | C14: =IFERROR(__xludf.DUMMYFUNCTION("""COMPUTED_VALUE"""),"YES!Delft") -> YES!Delft | D14: =IFERROR(__xludf.DUMMYFUNCTION("""COMPUTED_VALUE"""),"Head of Incubator") -> Head of Incubator | E14: =IFERROR(__xludf.DUMMYFUNCTION("""COMPUTED_VALUE"""),"Valuable connections") -> Valuable connections | F14: =IFERROR(__xludf.DUMMYFUNCTION("""COMPUTED_VALUE"""),"​Aerospace") -> ​Aerospace | H14: =VLOOKUP(B14,'new total list'!E:E,1,false) -> freek@yesdelft.nl | I14: =vlookup(A14,'new total list'!B:B,1,false) -> Freek Smoes | K14: =IF(AND(ISNA(H14), ISNA(I14)), "Marked", "") | L14: ? | M14: moshe
A15: =IFERROR(__xludf.DUMMYFUNCTION("""COMPUTED_VALUE"""),"Danique Engelberts") -> Danique Engelberts | B15: =IFERROR(__xludf.DUMMYFUNCTION("""COMPUTED_VALUE"""),"danique@yesdelft.nl") -> danique@yesdelft.nl | C15: =IFERROR(__xludf.DUMMYFUNCTION("""COMPUTED_VALUE"""),"YES!Delft") -> YES!Delft | D15: =IFERROR(__xludf.DUMMYFUNCTION("""COMPUTED_VALUE"""),"Event Manager") -> Event Manager | E15: =IFERROR(__xludf.DUMMYFUNCTION("""COMPUTED_VALUE"""),"Succes!") -> Succes! | F15: =IFERROR(__xludf.DUMMYFUNCTION("""COMPUTED_VALUE"""),"Energy") -> Energy | H15: =VLOOKUP(B15,'new total list'!E:E,1,false) -> Danique@yesdelft.nl | I15: =vlookup(A15,'new total list'!B:B,1,false) -> #N/A | K15: =IF(AND(ISNA(H15), ISNA(I15)), "Marked", "")
A16: =IFERROR(__xludf.DUMMYFUNCTION("""COMPUTED_VALUE"""),"Fabian Groeneveld") -> Fabian Groeneveld | B16: =IFERROR(__xludf.DUMMYFUNCTION("""COMPUTED_VALUE"""),"fabian.groeneveld@rabobank.nl") -> fabian.groeneveld@rabobank.nl | C16: =IFERROR(__xludf.DUMMYFUNCTION("""COMPUTED_VALUE"""),"Rabobank") -> Rabobank | D16: =IFERROR(__xludf.DUMMYFUNCTION("""COMPUTED_VALUE"""),"Startup & Scale-up Banker") -> Startup & Scale-up Banker | E16: =IFERROR(__xludf.DUMMYFUNCTION("""COMPUTED_VALUE"""),"Network connections") -> Network connections | F16: =IFERROR(__xludf.DUMMYFUNCTION("""COMPUTED_VALUE"""),"Maritime") -> Maritime | H16: =VLOOKUP(B16,'new total list'!E:E,1,false) -> fabian.groeneveld@rabobank.nl | I16: =vlookup(A16,'new total list'!B:B,1,false) -> Fabian Groeneveld | K16: =IF(AND(ISNA(H16), ISNA(I16)), "Marked", "")
A17: =IFERROR(__xludf.DUMMYFUNCTION("""COMPUTED_VALUE"""),"Daniel Kofman") -> Daniel Kofman | B17: =IFERROR(__xludf.DUMMYFUNCTION("""COMPUTED_VALUE"""),"daniel.kofman@siemens.com") -> daniel.kofman@siemens.com | C17: =IFERROR(__xludf.DUMMYFUNCTION("""COMPUTED_VALUE"""),"Siemens Digital Industries") -> Siemens Digital Industries | D17: =IFERROR(__xludf.DUMMYFUNCTION("""COMPUTED_VALUE"""),"Education Xcelerator") -> Education Xcelerator | E17: =IFERROR(__xludf.DUMMYFUNCTION("""COMPUTED_VALUE"""),"meet interesting startus to support") -> meet interesting startus to support | F17: =IFERROR(__xludf.DUMMYFUNCTION("""COMPUTED_VALUE"""),"Dual Use") -> Dual Use | H17: =VLOOKUP(B17,'new total list'!E:E,1,false) -> daniel.kofman@siemens.com | I17: =vlookup(A17,'new total list'!B:B,1,false) -> Daniel Kofman | K17: =IF(AND(ISNA(H17), ISNA(I17)), "Marked", "")
A18: =IFERROR(__xludf.DUMMYFUNCTION("""COMPUTED_VALUE"""),"Floris Blonk") -> Floris Blonk | B18: =IFERROR(__xludf.DUMMYFUNCTION("""COMPUTED_VALUE"""),"floris.blonk@energy-innovation.nl") -> floris.blonk@energy-innovation.nl | C18: =IFERROR(__xludf.DUMMYFUNCTION("""COMPUTED_VALUE"""),"Energy Innovation NL") -> Energy Innovation NL | D18: =IFERROR(__xludf.DUMMYFUNCTION("""COMPUTED_VALUE"""),"Program Manager") -> Program Manager | E18: =IFERROR(__xludf.DUMMYFUNCTION("""COMPUTED_VALUE"""),"Scout new offshore renewable energy startups") -> Scout new offshore renewable energy startups | F18: =IFERROR(__xludf.DUMMYFUNCTION("""COMPUTED_VALUE"""),"get insight in latest developments and needs.") -> get insight in latest developments and needs. | H18: =VLOOKUP(B18,'new total list'!E:E,1,false) -> #N/A | I18: =vlookup(A18,'new total list'!B:B,1,false) -> Floris Blonk | K18: =IF(AND(ISNA(H18), ISNA(I18)), "Marked", "")
A19: =IFERROR(__xludf.DUMMYFUNCTION("""COMPUTED_VALUE"""),"Anske Plante") -> Anske Plante | B19: =IFERROR(__xludf.DUMMYFUNCTION("""COMPUTED_VALUE"""),"j.a.plante@tudelft.nl") -> j.a.plante@tudelft.nl | C19: =IFERROR(__xludf.DUMMYFUNCTION("""COMPUTED_VALUE"""),"TU Delft - Technische Universiteit Delft") -> TU Delft - Technische Universiteit Delft | D19: =IFERROR(__xludf.DUMMYFUNCTION("""COMPUTED_VALUE"""),"Accountmanager") -> Accountmanager | E19: =IFERROR(__xludf.DUMMYFUNCTION("""COMPUTED_VALUE"""),"making connections between startups and sme") -> making connections between startups and sme | F19: =IFERROR(__xludf.DUMMYFUNCTION("""COMPUTED_VALUE"""),"Energy") -> Energy | H19: =VLOOKUP(B19,'new total list'!E:E,1,false) -> j.a.plante@tudelft.nl | I19: =vlookup(A19,'new total list'!B:B,1,false) -> Anske Plante | K19: =IF(AND(ISNA(H19), ISNA(I19)), "Marked", "")
A20: =IFERROR(__xludf.DUMMYFUNCTION("""COMPUTED_VALUE"""),"Jemy Pauwels") -> Jemy Pauwels | B20: =IFERROR(__xludf.DUMMYFUNCTION("""COMPUTED_VALUE"""),"jemy.pauwels@demcon.com") -> jemy.pauwels@demcon.com | C20: =IFERROR(__xludf.DUMMYFUNCTION("""COMPUTED_VALUE"""),"UDT TechFund by VDL & DEMCON") -> UDT TechFund by VDL & DEMCON | D20: =IFERROR(__xludf.DUMMYFUNCTION("""COMPUTED_VALUE"""),"Investment Director") -> Investment Director | E20: =IFERROR(__xludf.DUMMYFUNCTION("""COMPUTED_VALUE"""),"Investments") -> Investments | F20: =IFERROR(__xludf.DUMMYFUNCTION("""COMPUTED_VALUE"""),"Maritime") -> Maritime | H20: =VLOOKUP(B20,'new total list'!E:E,1,false) -> jemy.pauwels@demcon.com | I20: =vlookup(A20,'new total list'!B:B,1,false) -> Jemy Pauwels | K20: =IF(AND(ISNA(H20), ISNA(I20)), "Marked", "")
A21: =IFERROR(__xludf.DUMMYFUNCTION("""COMPUTED_VALUE"""),"brian stout") -> brian stout | B21: =IFERROR(__xludf.DUMMYFUNCTION("""COMPUTED_VALUE"""),"brian.stout@ziggo.nl") -> brian.stout@ziggo.nl | C21: =IFERROR(__xludf.DUMMYFUNCTION("""COMPUTED_VALUE"""),"Stout Managament Services BV") -> Stout Managament Services BV | D21: =IFERROR(__xludf.DUMMYFUNCTION("""COMPUTED_VALUE"""),"Directeur") -> Directeur | E21: =IFERROR(__xludf.DUMMYFUNCTION("""COMPUTED_VALUE"""),"To understand what new exciting ideas are there and how I can contribute as a mentor") -> To understand what new exciting ideas are there and how I can contribute as a mentor | F21: =IFERROR(__xludf.DUMMYFUNCTION("""COMPUTED_VALUE"""),"Dual Use") -> Dual Use | H21: =VLOOKUP(B21,'new total list'!E:E,1,false) -> brian.stout@ziggo.nl | I21: =vlookup(A21,'new total list'!B:B,1,false) -> Brian Stout | K21: =IF(AND(ISNA(H21), ISNA(I21)), "Marked", "")
A22: =IFERROR(__xludf.DUMMYFUNCTION("""COMPUTED_VALUE"""),"Tomba Paagman") -> Tomba Paagman | B22: =IFERROR(__xludf.DUMMYFUNCTION("""COMPUTED_VALUE"""),"tomba.paagman@campusatsea.nl") -> tomba.paagman@campusatsea.nl | C22: =IFERROR(__xludf.DUMMYFUNCTION("""COMPUTED_VALUE"""),"Campus@Sea") -> Campus@Sea | D22: =IFERROR(__xludf.DUMMYFUNCTION("""COMPUTED_VALUE"""),"Junior Project Manager") -> Junior Project Manager | E22: =IFERROR(__xludf.DUMMYFUNCTION("""COMPUTED_VALUE"""),"Learning the new generation of innovators") -> Learning the new generation of innovators | F22: =IFERROR(__xludf.DUMMYFUNCTION("""COMPUTED_VALUE"""),"Maritime") -> Maritime | H22: =VLOOKUP(B22,'new total list'!E:E,1,false) -> #N/A | I22: =vlookup(A22,'new total list'!B:B,1,false) -> #N/A | K22: =IF(AND(ISNA(H22), ISNA(I22)), "Marked", "") -> Marked
A23: =IFERROR(__xludf.DUMMYFUNCTION("""COMPUTED_VALUE"""),"Maarten van der Elst") -> Maarten van der Elst | B23: =IFERROR(__xludf.DUMMYFUNCTION("""COMPUTED_VALUE"""),"m.vanderelst@tudelft.nl") -> m.vanderelst@tudelft.nl | C23: =IFERROR(__xludf.DUMMYFUNCTION("""COMPUTED_VALUE"""),"Delft University of Technology") -> Delft University of Technology | D23: =IFERROR(__xludf.DUMMYFUNCTION("""COMPUTED_VALUE"""),"Prof dr") -> Prof dr | E23: =IFERROR(__xludf.DUMMYFUNCTION("""COMPUTED_VALUE"""),"To see what is new in healthtech") -> To see what is new in healthtech | F23: =IFERROR(__xludf.DUMMYFUNCTION("""COMPUTED_VALUE"""),"MedTech") -> MedTech | H23: =VLOOKUP(B23,'new total list'!E:E,1,false) -> M.vanderElst@tudelft.nl | I23: =vlookup(A23,'new total list'!B:B,1,false) -> Maarten van der Elst | K23: =IF(AND(ISNA(H23), ISNA(I23)), "Marked", "")
A24: =IFERROR(__xludf.DUMMYFUNCTION("""COMPUTED_VALUE"""),"Joris Meijaard") -> Joris Meijaard | B24: =IFERROR(__xludf.DUMMYFUNCTION("""COMPUTED_VALUE"""),"meijaard@rsm.nl") -> meijaard@rsm.nl | C24: =IFERROR(__xludf.DUMMYFUNCTION("""COMPUTED_VALUE"""),"RSM/MIR/Yes!Delft") -> RSM/MIR/Yes!Delft | D24: =IFERROR(__xludf.DUMMYFUNCTION("""COMPUTED_VALUE"""),"Academic director") -> Academic director | E24: =IFERROR(__xludf.DUMMYFUNCTION("""COMPUTED_VALUE"""),"Inspiration") -> Inspiration | F24: =IFERROR(__xludf.DUMMYFUNCTION("""COMPUTED_VALUE"""),"​Aerospace") -> ​Aerospace | H24: =VLOOKUP(B24,'new total list'!E:E,1,false) -> meijaard@rsm.nl | I24: =vlookup(A24,'new total list'!B:B,1,false) -> Joris Meijaard | K24: =IF(AND(ISNA(H24), ISNA(I24)), "Marked", "")
A25: =IFERROR(__xludf.DUMMYFUNCTION("""COMPUTED_VALUE"""),"Philip Hess") -> Philip Hess | B25: =IFERROR(__xludf.DUMMYFUNCTION("""COMPUTED_VALUE"""),"p.hess@rotterdamfactoring.nl") -> p.hess@rotterdamfactoring.nl | C25: =IFERROR(__xludf.DUMMYFUNCTION("""COMPUTED_VALUE"""),"Rotterdam Factoring") -> Rotterdam Factoring | D25: =IFERROR(__xludf.DUMMYFUNCTION("""COMPUTED_VALUE"""),"CEO") -> CEO | E25: =IFERROR(__xludf.DUMMYFUNCTION("""COMPUTED_VALUE"""),"Connections and ideas") -> Connections and ideas | F25: =IFERROR(__xludf.DUMMYFUNCTION("""COMPUTED_VALUE"""),"Energy") -> Energy | H25: =VLOOKUP(B25,'new total list'!E:E,1,false) -> p.hess@rotterdamfactoring.nl | I25: =vlookup(A25,'new total list'!B:B,1,false) -> Philip Hess | K25: =IF(AND(ISNA(H25), ISNA(I25)), "Marked", "")
A26: =IFERROR(__xludf.DUMMYFUNCTION("""COMPUTED_VALUE"""),"Loet Rummenie") -> Loet Rummenie | B26: =IFERROR(__xludf.DUMMYFUNCTION("""COMPUTED_VALUE"""),"loet.rummenie@hiceu.com") -> loet.rummenie@hiceu.com | C26: =IFERROR(__xludf.DUMMYFUNCTION("""COMPUTED_VALUE"""),"HIC") -> HIC | D26: =IFERROR(__xludf.DUMMYFUNCTION("""COMPUTED_VALUE"""),"Managing Director") -> Managing Director | E26: =IFERROR(__xludf.DUMMYFUNCTION("""COMPUTED_VALUE"""),"network") -> network | F26: =IFERROR(__xludf.DUMMYFUNCTION("""COMPUTED_VALUE"""),"Energy") -> Energy | H26: =VLOOKUP(B26,'new total list'!E:E,1,false) -> loet.rummenie@hiceu.com | I26: =vlookup(A26,'new total list'!B:B,1,false) -> Loet Rummenie | K26: =IF(AND(ISNA(H26), ISNA(I26)), "Marked", "")
A27: =IFERROR(__xludf.DUMMYFUNCTION("""COMPUTED_VALUE"""),"Marlies Lukkes") -> Marlies Lukkes | B27: =IFERROR(__xludf.DUMMYFUNCTION("""COMPUTED_VALUE"""),"m.lukkes@shell.com") -> m.lukkes@shell.com | C27: =IFERROR(__xludf.DUMMYFUNCTION("""COMPUTED_VALUE"""),"Shell") -> Shell | D27: =IFERROR(__xludf.DUMMYFUNCTION("""COMPUTED_VALUE"""),"Commercial partnership manager") -> Commercial partnership manager | E27: =IFERROR(__xludf.DUMMYFUNCTION("""COMPUTED_VALUE"""),"connect with startups and wider ecosystem") -> connect with startups and wider ecosystem | F27: =IFERROR(__xludf.DUMMYFUNCTION("""COMPUTED_VALUE"""),"Maritime") -> Maritime | H27: =VLOOKUP(B27,'new total list'!E:E,1,false) -> m.lukkes@shell.com | I27: =vlookup(A27,'new total list'!B:B,1,false) -> Marlies Lukkes | K27: =IF(AND(ISNA(H27), ISNA(I27)), "Marked", "")
A28: =IFERROR(__xludf.DUMMYFUNCTION("""COMPUTED_VALUE"""),"Jelle Post") -> Jelle Post | B28: =IFERROR(__xludf.DUMMYFUNCTION("""COMPUTED_VALUE"""),"jelle.post@tudelft.nl") -> jelle.post@tudelft.nl | C28: =IFERROR(__xludf.DUMMYFUNCTION("""COMPUTED_VALUE"""),"Delft Enterprises") -> Delft Enterprises | D28: =IFERROR(__xludf.DUMMYFUNCTION("""COMPUTED_VALUE"""),"Investment Manager") -> Investment Manager | E28: =IFERROR(__xludf.DUMMYFUNCTION("""COMPUTED_VALUE"""),"Supporting our spin-offs & network") -> Supporting our spin-offs & network | F28: =IFERROR(__xludf.DUMMYFUNCTION("""COMPUTED_VALUE"""),"​Future of Compute") -> ​Future of Compute | H28: =VLOOKUP(B28,'new total list'!E:E,1,false) -> jelle.post@tudelft.nl | I28: =vlookup(A28,'new total list'!B:B,1,false) -> Jelle Post | K28: =IF(AND(ISNA(H28), ISNA(I28)), "Marked", "")
A29: =IFERROR(__xludf.DUMMYFUNCTION("""COMPUTED_VALUE"""),"richard. van der Vegt") -> richard. van der Vegt | B29: =IFERROR(__xludf.DUMMYFUNCTION("""COMPUTED_VALUE"""),"rg.vd.vegt@mindef.nl") -> rg.vd.vegt@mindef.nl | C29: =IFERROR(__xludf.DUMMYFUNCTION("""COMPUTED_VALUE"""),"TNO DSS") -> TNO DSS | D29: =IFERROR(__xludf.DUMMYFUNCTION("""COMPUTED_VALUE"""),"Business Manager") -> Business Manager | E29: =IFERROR(__xludf.DUMMYFUNCTION("""COMPUTED_VALUE"""),"learning") -> learning | F29: =IFERROR(__xludf.DUMMYFUNCTION("""COMPUTED_VALUE"""),"Dual Use") -> Dual Use | H29: =VLOOKUP(B29,'new total list'!E:E,1,false) -> rg.vd.vegt@mindef.nl | I29: =vlookup(A29,'new total list'!B:B,1,false) -> #N/A | K29: =IF(AND(ISNA(H29), ISNA(I29)), "Marked", "")
A30: =IFERROR(__xludf.DUMMYFUNCTION("""COMPUTED_VALUE"""),"Sander Peltenburg") -> Sander Peltenburg | B30: =IFERROR(__xludf.DUMMYFUNCTION("""COMPUTED_VALUE"""),"sander.peltenburg@rabobank.nl") -> sander.peltenburg@rabobank.nl | C30: =IFERROR(__xludf.DUMMYFUNCTION("""COMPUTED_VALUE"""),"Rabobank") -> Rabobank | D30: =IFERROR(__xludf.DUMMYFUNCTION("""COMPUTED_VALUE"""),"start and scaleup banker") -> start and scaleup banker | E30: =IFERROR(__xludf.DUMMYFUNCTION("""COMPUTED_VALUE"""),"meet the startups") -> meet the startups | F30: =IFERROR(__xludf.DUMMYFUNCTION("""COMPUTED_VALUE"""),"Energy") -> Energy | H30: =VLOOKUP(B30,'new total list'!E:E,1,false) -> sander.peltenburg@rabobank.nl | I30: =vlookup(A30,'new total list'!B:B,1,false) -> Sander Peltenburg | K30: =IF(AND(ISNA(H30), ISNA(I30)), "Marked", "")
A31: =IFERROR(__xludf.DUMMYFUNCTION("""COMPUTED_VALUE"""),"renze blokland") -> renze blokland | B31: =IFERROR(__xludf.DUMMYFUNCTION("""COMPUTED_VALUE"""),"renze.blokland@fme.nl") -> renze.blokland@fme.nl | C31: =IFERROR(__xludf.DUMMYFUNCTION("""COMPUTED_VALUE"""),"FME") -> FME | D31: =IFERROR(__xludf.DUMMYFUNCTION("""COMPUTED_VALUE"""),"funding advisor") -> funding advisor | E31: =IFERROR(__xludf.DUMMYFUNCTION("""COMPUTED_VALUE"""),"connections with start/scale ups") -> connections with start/scale ups | F31: =IFERROR(__xludf.DUMMYFUNCTION("""COMPUTED_VALUE"""),"​Aerospace") -> ​Aerospace | H31: =VLOOKUP(B31,'new total list'!E:E,1,false) -> renze.blokland@fme.nl | I31: =vlookup(A31,'new total list'!B:B,1,false) -> Renze Blokland | K31: =IF(AND(ISNA(H31), ISNA(I31)), "Marked", "")
A32: =IFERROR(__xludf.DUMMYFUNCTION("""COMPUTED_VALUE"""),"Nina Donker") -> Nina Donker | B32: =IFERROR(__xludf.DUMMYFUNCTION("""COMPUTED_VALUE"""),"nina@capitaltvc.com") -> nina@capitaltvc.com | C32: =IFERROR(__xludf.DUMMYFUNCTION("""COMPUTED_VALUE"""),"CapitalT") -> CapitalT | D32: =IFERROR(__xludf.DUMMYFUNCTION("""COMPUTED_VALUE"""),"Investment Associate") -> Investment Associate | E32: =IFERROR(__xludf.DUMMYFUNCTION("""COMPUTED_VALUE"""),"Network") -> Network | F32: =IFERROR(__xludf.DUMMYFUNCTION("""COMPUTED_VALUE"""),"Energy") -> Energy | H32: =VLOOKUP(B32,'new total list'!E:E,1,false) -> nina@capitaltvc.com | I32: =vlookup(A32,'new total list'!B:B,1,false) -> Nina Donker | K32: =IF(AND(ISNA(H32), ISNA(I32)), "Marked", "")
A33: =IFERROR(__xludf.DUMMYFUNCTION("""COMPUTED_VALUE"""),"Aman Jindal") -> Aman Jindal | B33: =IFERROR(__xludf.DUMMYFUNCTION("""COMPUTED_VALUE"""),"aman.jindal@denoize.com") -> aman.jindal@denoize.com | C33: =IFERROR(__xludf.DUMMYFUNCTION("""COMPUTED_VALUE"""),"DeNoize B.V.") -> DeNoize B.V. | D33: =IFERROR(__xludf.DUMMYFUNCTION("""COMPUTED_VALUE"""),"CEO") -> CEO | E33: =IFERROR(__xludf.DUMMYFUNCTION("""COMPUTED_VALUE"""),"Network") -> Network | F33: =IFERROR(__xludf.DUMMYFUNCTION("""COMPUTED_VALUE"""),"Dual Use") -> Dual Use | H33: =VLOOKUP(B33,'new total list'!E:E,1,false) -> aman.jindal@denoize.com | I33: =vlookup(A33,'new total list'!B:B,1,false) -> Aman Jindal | K33: =IF(AND(ISNA(H33), ISNA(I33)), "Marked", "")
A34: =IFERROR(__xludf.DUMMYFUNCTION("""COMPUTED_VALUE"""),"Simone van Schijndel") -> Simone van Schijndel | B34: =IFERROR(__xludf.DUMMYFUNCTION("""COMPUTED_VALUE"""),"s.a.h.vanschijndel@tudelft.nl") -> s.a.h.vanschijndel@tudelft.nl | C34: =IFERROR(__xludf.DUMMYFUNCTION("""COMPUTED_VALUE"""),"TU Delft") -> TU Delft | D34: =IFERROR(__xludf.DUMMYFUNCTION("""COMPUTED_VALUE"""),"Head Program & Partnership Development") -> Head Program & Partnership Development | E34: =IFERROR(__xludf.DUMMYFUNCTION("""COMPUTED_VALUE"""),"get to know the startups in the TU Delft ecosystem") -> get to know the startups in the TU Delft ecosystem | F34: =IFERROR(__xludf.DUMMYFUNCTION("""COMPUTED_VALUE"""),"Maritime") -> Maritime | H34: =VLOOKUP(B34,'new total list'!E:E,1,false) -> s.a.h.vanschijndel@tudelft.nl | I34: =vlookup(A34,'new total list'!B:B,1,false) -> Simone van Schijndel | K34: =IF(AND(ISNA(H34), ISNA(I34)), "Marked", "")
A35: =IFERROR(__xludf.DUMMYFUNCTION("""COMPUTED_VALUE"""),"Jacqueline Papendrecht") -> Jacqueline Papendrecht | B35: =IFERROR(__xludf.DUMMYFUNCTION("""COMPUTED_VALUE"""),"j.papendrecht@tudelft.nl") -> j.papendrecht@tudelft.nl | C35: =IFERROR(__xludf.DUMMYFUNCTION("""COMPUTED_VALUE"""),"TU DELFT CAMPUS") -> TU DELFT CAMPUS | D35: =IFERROR(__xludf.DUMMYFUNCTION("""COMPUTED_VALUE"""),"accountmanager") -> accountmanager | E35: =IFERROR(__xludf.DUMMYFUNCTION("""COMPUTED_VALUE"""),"networking") -> networking | F35: =IFERROR(__xludf.DUMMYFUNCTION("""COMPUTED_VALUE"""),"Dual Use") -> Dual Use | H35: =VLOOKUP(B35,'new total list'!E:E,1,false) -> j.papendrecht@tudelft.nl | I35: =vlookup(A35,'new total list'!B:B,1,false) -> Jacqueline Papendrecht | K35: =IF(AND(ISNA(H35), ISNA(I35)), "Marked", "")
A36: =IFERROR(__xludf.DUMMYFUNCTION("""COMPUTED_VALUE"""),"Luuk Mur") -> Luuk Mur | B36: =IFERROR(__xludf.DUMMYFUNCTION("""COMPUTED_VALUE"""),"l.c.mur@tudelft.nl") -> l.c.mur@tudelft.nl | C36: =IFERROR(__xludf.DUMMYFUNCTION("""COMPUTED_VALUE"""),"TU Delft") -> TU Delft | D36: =IFERROR(__xludf.DUMMYFUNCTION("""COMPUTED_VALUE"""),"Policy Advisor") -> Policy Advisor | E36: =IFERROR(__xludf.DUMMYFUNCTION("""COMPUTED_VALUE"""),"Obtain deeper insights into how TU Delft can better support the development of startups") -> Obtain deeper insights into how TU Delft can better support the development of startups | F36: =IFERROR(__xludf.DUMMYFUNCTION("""COMPUTED_VALUE"""),"​Aerospace") -> ​Aerospace | H36: =VLOOKUP(B36,'new total list'!E:E,1,false) -> l.c.mur@tudelft.nl | I36: =vlookup(A36,'new total list'!B:B,1,false) -> Luuk Mur | K36: =IF(AND(ISNA(H36), ISNA(I36)), "Marked", "")
A37: =IFERROR(__xludf.DUMMYFUNCTION("""COMPUTED_VALUE"""),"Sander Vroom") -> Sander Vroom | B37: =IFERROR(__xludf.DUMMYFUNCTION("""COMPUTED_VALUE"""),"sandervroom@gmail.com") -> sandervroom@gmail.com | C37: =IFERROR(__xludf.DUMMYFUNCTION("""COMPUTED_VALUE"""),"Rabobank") -> Rabobank | D37: =IFERROR(__xludf.DUMMYFUNCTION("""COMPUTED_VALUE"""),"Business Development Manager") -> Business Development Manager | E37: =IFERROR(__xludf.DUMMYFUNCTION("""COMPUTED_VALUE"""),"New contacts within foodsystem-") -> New contacts within foodsystem- | F37: =IFERROR(__xludf.DUMMYFUNCTION("""COMPUTED_VALUE"""),"agtech- and energytransition. And catching up with acquaintances.") -> agtech- and energytransition. And catching up with acquaintances. | H37: =VLOOKUP(B37,'new total list'!E:E,1,false) -> #N/A | I37: =vlookup(A37,'new total list'!B:B,1,false) -> Sander Vroom | K37: =IF(AND(ISNA(H37), ISNA(I37)), "Marked", "")
A38: =IFERROR(__xludf.DUMMYFUNCTION("""COMPUTED_VALUE"""),"sjoerd mol") -> sjoerd mol | B38: =IFERROR(__xludf.DUMMYFUNCTION("""COMPUTED_VALUE"""),"mol@benvalor.com") -> mol@benvalor.com | C38: =IFERROR(__xludf.DUMMYFUNCTION("""COMPUTED_VALUE"""),"Benvalor") -> Benvalor | D38: =IFERROR(__xludf.DUMMYFUNCTION("""COMPUTED_VALUE"""),"Partner") -> Partner | E38: =IFERROR(__xludf.DUMMYFUNCTION("""COMPUTED_VALUE"""),"Meeting interesting startups") -> Meeting interesting startups | F38: =IFERROR(__xludf.DUMMYFUNCTION("""COMPUTED_VALUE"""),"​Future of Compute") -> ​Future of Compute | H38: =VLOOKUP(B38,'new total list'!E:E,1,false) -> mol@benvalor.com | I38: =vlookup(A38,'new total list'!B:B,1,false) -> Sjoerd Mol | K38: =IF(AND(ISNA(H38), ISNA(I38)), "Marked", "")
A39: =IFERROR(__xludf.DUMMYFUNCTION("""COMPUTED_VALUE"""),"Kirsten Ruiter") -> Kirsten Ruiter | B39: =IFERROR(__xludf.DUMMYFUNCTION("""COMPUTED_VALUE"""),"kirsten.ruiter@buccaneerdelft.com") -> kirsten.ruiter@buccaneerdelft.com | C39: =IFERROR(__xludf.DUMMYFUNCTION("""COMPUTED_VALUE"""),"Buccaneer Delft") -> Buccaneer Delft | D39: =IFERROR(__xludf.DUMMYFUNCTION("""COMPUTED_VALUE"""),"Managing Director") -> Managing Director | E39: =IFERROR(__xludf.DUMMYFUNCTION("""COMPUTED_VALUE"""),"Meeting new startups") -> Meeting new startups | F39: =IFERROR(__xludf.DUMMYFUNCTION("""COMPUTED_VALUE"""),"seeing innovations") -> seeing innovations | H39: =VLOOKUP(B39,'new total list'!E:E,1,false) -> kirsten.ruiter@buccaneerdelft.com | I39: =vlookup(A39,'new total list'!B:B,1,false) -> Kirsten Ruiter | K39: =IF(AND(ISNA(H39), ISNA(I39)), "Marked", "")
A40: =IFERROR(__xludf.DUMMYFUNCTION("""COMPUTED_VALUE"""),"Henk van Groen") -> Henk van Groen | B40: =IFERROR(__xludf.DUMMYFUNCTION("""COMPUTED_VALUE"""),"henk@percivalparticipations.com") -> henk@percivalparticipations.com | C40: =IFERROR(__xludf.DUMMYFUNCTION("""COMPUTED_VALUE"""),"Percival Participations BV") -> Percival Participations BV | D40: =IFERROR(__xludf.DUMMYFUNCTION("""COMPUTED_VALUE"""),"Director") -> Director | E40: =IFERROR(__xludf.DUMMYFUNCTION("""COMPUTED_VALUE"""),"Ideas") -> Ideas | F40: =IFERROR(__xludf.DUMMYFUNCTION("""COMPUTED_VALUE"""),"Energy") -> Energy | H40: =VLOOKUP(B40,'new total list'!E:E,1,false) -> #N/A | I40: =vlookup(A40,'new total list'!B:B,1,false) -> Henk van Groen | K40: =IF(AND(ISNA(H40), ISNA(I40)), "Marked", "")
A41: =IFERROR(__xludf.DUMMYFUNCTION("""COMPUTED_VALUE"""),"Ellen") -> Ellen | B41: =IFERROR(__xludf.DUMMYFUNCTION("""COMPUTED_VALUE"""),"em.vandam@cornelderholding.com") -> em.vandam@cornelderholding.com | C41: =IFERROR(__xludf.DUMMYFUNCTION("""COMPUTED_VALUE"""),"Cornelder Holding B.V.") -> Cornelder Holding B.V. | D41: =IFERROR(__xludf.DUMMYFUNCTION("""COMPUTED_VALUE"""),"CEO") -> CEO | E41: =IFERROR(__xludf.DUMMYFUNCTION("""COMPUTED_VALUE"""),"To connect with promising startups") -> To connect with promising startups | F41: =IFERROR(__xludf.DUMMYFUNCTION("""COMPUTED_VALUE"""),"gain insights into new technologies and industry trends") -> gain insights into new technologies and industry trends | H41: =VLOOKUP(B41,'new total list'!E:E,1,false) -> em.vandam@cornelderholding.com | I41: =vlookup(A41,'new total list'!B:B,1,false) -> #N/A | K41: =IF(AND(ISNA(H41), ISNA(I41)), "Marked", "")
A42: =IFERROR(__xludf.DUMMYFUNCTION("""COMPUTED_VALUE"""),"Sjoerd Stevens") -> Sjoerd Stevens | B42: =IFERROR(__xludf.DUMMYFUNCTION("""COMPUTED_VALUE"""),"sjoerd@norrskenevolve.vc") -> sjoerd@norrskenevolve.vc | C42: =IFERROR(__xludf.DUMMYFUNCTION("""COMPUTED_VALUE"""),"Norrsken Evolve") -> Norrsken Evolve | D42: =IFERROR(__xludf.DUMMYFUNCTION("""COMPUTED_VALUE"""),"Investor") -> Investor | E42: =IFERROR(__xludf.DUMMYFUNCTION("""COMPUTED_VALUE"""),"Meeting startups") -> Meeting startups | F42: =IFERROR(__xludf.DUMMYFUNCTION("""COMPUTED_VALUE"""),"Energy") -> Energy | H42: =VLOOKUP(B42,'new total list'!E:E,1,false) -> #N/A | I42: =vlookup(A42,'new total list'!B:B,1,false) -> Sjoerd Stevens | K42: =IF(AND(ISNA(H42), ISNA(I42)), "Marked", "")
A43: =IFERROR(__xludf.DUMMYFUNCTION("""COMPUTED_VALUE"""),"Yannick Hopf") -> Yannick Hopf | B43: =IFERROR(__xludf.DUMMYFUNCTION("""COMPUTED_VALUE"""),"yhopf@sonosilicon.com") -> yhopf@sonosilicon.com | C43: =IFERROR(__xludf.DUMMYFUNCTION("""COMPUTED_VALUE"""),"Sonosilicon") -> Sonosilicon | D43: =IFERROR(__xludf.DUMMYFUNCTION("""COMPUTED_VALUE"""),"Co-Founder") -> Co-Founder | E43: =IFERROR(__xludf.DUMMYFUNCTION("""COMPUTED_VALUE"""),"Connection making") -> Connection making | F43: =IFERROR(__xludf.DUMMYFUNCTION("""COMPUTED_VALUE"""),"MedTech") -> MedTech | H43: =VLOOKUP(B43,'new total list'!E:E,1,false) -> yhopf@sonosilicon.com | I43: =vlookup(A43,'new total list'!B:B,1,false) -> Yannick Hopf | K43: =IF(AND(ISNA(H43), ISNA(I43)), "Marked", "") | L43: FOUTJE
A44: =IFERROR(__xludf.DUMMYFUNCTION("""COMPUTED_VALUE"""),"Vincent Ruijter") -> Vincent Ruijter | B44: =IFERROR(__xludf.DUMMYFUNCTION("""COMPUTED_VALUE"""),"vincent.ruijter@gmail.com") -> vincent.ruijter@gmail.com | C44: =IFERROR(__xludf.DUMMYFUNCTION("""COMPUTED_VALUE"""),"Impact ready") -> Impact ready | D44: =IFERROR(__xludf.DUMMYFUNCTION("""COMPUTED_VALUE"""),"Director") -> Director | E44: =IFERROR(__xludf.DUMMYFUNCTION("""COMPUTED_VALUE"""),"Meeting startups") -> Meeting startups | F44: =IFERROR(__xludf.DUMMYFUNCTION("""COMPUTED_VALUE"""),"Energy") -> Energy | H44: =VLOOKUP(B44,'new total list'!E:E,1,false) -> vincent.ruijter@gmail.com | I44: =vlookup(A44,'new total list'!B:B,1,false) -> Vincent Ruijter | K44: =IF(AND(ISNA(H44), ISNA(I44)), "Marked", "")
A45: =IFERROR(__xludf.DUMMYFUNCTION("""COMPUTED_VALUE"""),"Ide Swager") -> Ide Swager | B45: =IFERROR(__xludf.DUMMYFUNCTION("""COMPUTED_VALUE"""),"ide@swager.eu") -> ide@swager.eu | C45: =IFERROR(__xludf.DUMMYFUNCTION("""COMPUTED_VALUE"""),"Freelance / Momo Medical") -> Freelance / Momo Medical | D45: =IFERROR(__xludf.DUMMYFUNCTION("""COMPUTED_VALUE"""),"Consultant & Coach") -> Consultant & Coach | E45: =IFERROR(__xludf.DUMMYFUNCTION("""COMPUTED_VALUE"""),"Expand and reconnect with Y!D network") -> Expand and reconnect with Y!D network | F45: =IFERROR(__xludf.DUMMYFUNCTION("""COMPUTED_VALUE"""),"meet new start-ups") -> meet new start-ups | H45: =VLOOKUP(B45,'new total list'!E:E,1,false) -> #N/A | I45: =vlookup(A45,'new total list'!B:B,1,false) -> Ide Swager | K45: =IF(AND(ISNA(H45), ISNA(I45)), "Marked", "")
A46: =IFERROR(__xludf.DUMMYFUNCTION("""COMPUTED_VALUE"""),"Tsuyoshi Yamashita") -> Tsuyoshi Yamashita | B46: =IFERROR(__xludf.DUMMYFUNCTION("""COMPUTED_VALUE"""),"tsuyoshi_yamashita@murata.com") -> tsuyoshi_yamashita@murata.com | C46: =IFERROR(__xludf.DUMMYFUNCTION("""COMPUTED_VALUE"""),"WONDERSTONE Ventures") -> WONDERSTONE Ventures | D46: =IFERROR(__xludf.DUMMYFUNCTION("""COMPUTED_VALUE"""),"Director") -> Director | E46: =IFERROR(__xludf.DUMMYFUNCTION("""COMPUTED_VALUE"""),"New startup information and networking") -> New startup information and networking | F46: =IFERROR(__xludf.DUMMYFUNCTION("""COMPUTED_VALUE"""),"​Aerospace") -> ​Aerospace | H46: =VLOOKUP(B46,'new total list'!E:E,1,false) -> tsuyoshi_yamashita@murata.com | I46: =vlookup(A46,'new total list'!B:B,1,false) -> Tsuyoshi Yamashita | K46: =IF(AND(ISNA(H46), ISNA(I46)), "Marked", "")
A47: =IFERROR(__xludf.DUMMYFUNCTION("""COMPUTED_VALUE"""),"Fatih Kaya") -> Fatih Kaya | B47: =IFERROR(__xludf.DUMMYFUNCTION("""COMPUTED_VALUE"""),"f.kaya@kikkcapital.com") -> f.kaya@kikkcapital.com | C47: =IFERROR(__xludf.DUMMYFUNCTION("""COMPUTED_VALUE"""),"KIKK Capital") -> KIKK Capital | D47: =IFERROR(__xludf.DUMMYFUNCTION("""COMPUTED_VALUE"""),"Investment Manager") -> Investment Manager | E47: =IFERROR(__xludf.DUMMYFUNCTION("""COMPUTED_VALUE"""),"Hopefully some interesting leads.") -> Hopefully some interesting leads. | F47: =IFERROR(__xludf.DUMMYFUNCTION("""COMPUTED_VALUE"""),"Dual Use") -> Dual Use | H47: =VLOOKUP(B47,'new total list'!E:E,1,false) -> f.kaya@kikkcapital.com | I47: =vlookup(A47,'new total list'!B:B,1,false) -> Fatih Kaya | K47: =IF(AND(ISNA(H47), ISNA(I47)), "Marked", "")
A48: =IFERROR(__xludf.DUMMYFUNCTION("""COMPUTED_VALUE"""),"Joris van Kappen") -> Joris van Kappen | B48: =IFERROR(__xludf.DUMMYFUNCTION("""COMPUTED_VALUE"""),"joris@van-kappen.com") -> joris@van-kappen.com | C48: =IFERROR(__xludf.DUMMYFUNCTION("""COMPUTED_VALUE"""),"Accelor Hub") -> Accelor Hub | D48: =IFERROR(__xludf.DUMMYFUNCTION("""COMPUTED_VALUE"""),"Founder & GTM Strategist") -> Founder & GTM Strategist | E48: =IFERROR(__xludf.DUMMYFUNCTION("""COMPUTED_VALUE"""),"Meet the new startups") -> Meet the new startups | F48: =IFERROR(__xludf.DUMMYFUNCTION("""COMPUTED_VALUE"""),"learn what they are building") -> learn what they are building | H48: =VLOOKUP(B48,'new total list'!E:E,1,false) -> joris@van-kappen.com | I48: =vlookup(A48,'new total list'!B:B,1,false) -> Joris van Kappen | K48: =IF(AND(ISNA(H48), ISNA(I48)), "Marked", "")
A49: =IFERROR(__xludf.DUMMYFUNCTION("""COMPUTED_VALUE"""),"Richard Illes") -> Richard Illes | B49: =IFERROR(__xludf.DUMMYFUNCTION("""COMPUTED_VALUE"""),"richard.illes@o3.partners") -> richard.illes@o3.partners | C49: =IFERROR(__xludf.DUMMYFUNCTION("""COMPUTED_VALUE"""),"O3 Partners N.V.") -> O3 Partners N.V. | D49: =IFERROR(__xludf.DUMMYFUNCTION("""COMPUTED_VALUE"""),"Investment Director") -> Investment Director | E49: =IFERROR(__xludf.DUMMYFUNCTION("""COMPUTED_VALUE"""),"great meetings with sharp founders") -> great meetings with sharp founders | F49: =IFERROR(__xludf.DUMMYFUNCTION("""COMPUTED_VALUE"""),"Energy") -> Energy | H49: =VLOOKUP(B49,'new total list'!E:E,1,false) -> #N/A | I49: =vlookup(A49,'new total list'!B:B,1,false) -> Richard Illes | K49: =IF(AND(ISNA(H49), ISNA(I49)), "Marked", "")
A50: =IFERROR(__xludf.DUMMYFUNCTION("""COMPUTED_VALUE"""),"Mathijs van der Knaap") -> Mathijs van der Knaap | B50: =IFERROR(__xludf.DUMMYFUNCTION("""COMPUTED_VALUE"""),"mathijs@vpcapital.eu") -> mathijs@vpcapital.eu | C50: =IFERROR(__xludf.DUMMYFUNCTION("""COMPUTED_VALUE"""),"VP Capital") -> VP Capital | D50: =IFERROR(__xludf.DUMMYFUNCTION("""COMPUTED_VALUE"""),"Investment Manager") -> Investment Manager | E50: =IFERROR(__xludf.DUMMYFUNCTION("""COMPUTED_VALUE"""),"Network and find investment opportunities") -> Network and find investment opportunities | F50: =IFERROR(__xludf.DUMMYFUNCTION("""COMPUTED_VALUE"""),"Energy") -> Energy | H50: =VLOOKUP(B50,'new total list'!E:E,1,false) -> mathijs@vpcapital.eu | I50: =vlookup(A50,'new total list'!B:B,1,false) -> Mathijs Van Der Knaap | K50: =IF(AND(ISNA(H50), ISNA(I50)), "Marked", "")
A51: =IFERROR(__xludf.DUMMYFUNCTION("""COMPUTED_VALUE"""),"Karlijn van de Kamp") -> Karlijn van de Kamp | B51: =IFERROR(__xludf.DUMMYFUNCTION("""COMPUTED_VALUE"""),"k.kamp@portofrotterdam.com") -> k.kamp@portofrotterdam.com | C51: =IFERROR(__xludf.DUMMYFUNCTION("""COMPUTED_VALUE"""),"Port of Rotterdam") -> Port of Rotterdam | D51: =IFERROR(__xludf.DUMMYFUNCTION("""COMPUTED_VALUE"""),"Business Development Manager Bedrijven") -> Business Development Manager Bedrijven | E51: =IFERROR(__xludf.DUMMYFUNCTION("""COMPUTED_VALUE"""),"Connection") -> Connection | F51: =IFERROR(__xludf.DUMMYFUNCTION("""COMPUTED_VALUE"""),"Maritime") -> Maritime | H51: =VLOOKUP(B51,'new total list'!E:E,1,false) -> #N/A | I51: =vlookup(A51,'new total list'!B:B,1,false) -> #N/A | K51: =IF(AND(ISNA(H51), ISNA(I51)), "Marked", "") -> Marked
A52: =IFERROR(__xludf.DUMMYFUNCTION("""COMPUTED_VALUE"""),"Remy Kesrouani") -> Remy Kesrouani | B52: =IFERROR(__xludf.DUMMYFUNCTION("""COMPUTED_VALUE"""),"remy@kadmoscapital.com") -> remy@kadmoscapital.com | C52: =IFERROR(__xludf.DUMMYFUNCTION("""COMPUTED_VALUE"""),"Kadmos Capital") -> Kadmos Capital | D52: =IFERROR(__xludf.DUMMYFUNCTION("""COMPUTED_VALUE"""),"Managing Partner") -> Managing Partner | E52: =IFERROR(__xludf.DUMMYFUNCTION("""COMPUTED_VALUE"""),"invest") -> invest | F52: =IFERROR(__xludf.DUMMYFUNCTION("""COMPUTED_VALUE"""),"Energy") -> Energy | H52: =VLOOKUP(B52,'new total list'!E:E,1,false) -> remy@kadmoscapital.com | I52: =vlookup(A52,'new total list'!B:B,1,false) -> Remy Kesrouani | K52: =IF(AND(ISNA(H52), ISNA(I52)), "Marked", "")
A53: =IFERROR(__xludf.DUMMYFUNCTION("""COMPUTED_VALUE"""),"J. Theunissen") -> J. Theunissen | B53: =IFERROR(__xludf.DUMMYFUNCTION("""COMPUTED_VALUE"""),"j.theunissen@kikkcapital.com") -> j.theunissen@kikkcapital.com | C53: =IFERROR(__xludf.DUMMYFUNCTION("""COMPUTED_VALUE"""),"KIKK Capital") -> KIKK Capital | D53: =IFERROR(__xludf.DUMMYFUNCTION("""COMPUTED_VALUE"""),"Sr. Investment Manager") -> Sr. Investment Manager | E53: =IFERROR(__xludf.DUMMYFUNCTION("""COMPUTED_VALUE"""),"meet interesting leads") -> meet interesting leads | F53: =IFERROR(__xludf.DUMMYFUNCTION("""COMPUTED_VALUE"""),"Dual Use") -> Dual Use | H53: =VLOOKUP(B53,'new total list'!E:E,1,false) -> j.theunissen@kikkcapital.com | I53: =vlookup(A53,'new total list'!B:B,1,false) -> #N/A | K53: =IF(AND(ISNA(H53), ISNA(I53)), "Marked", "")
A54: =IFERROR(__xludf.DUMMYFUNCTION("""COMPUTED_VALUE"""),"Philip Bueters") -> Philip Bueters | B54: =IFERROR(__xludf.DUMMYFUNCTION("""COMPUTED_VALUE"""),"philip@mtsprout.nl") -> philip@mtsprout.nl | C54: =IFERROR(__xludf.DUMMYFUNCTION("""COMPUTED_VALUE"""),"MT Mediagroep") -> MT Mediagroep | D54: =IFERROR(__xludf.DUMMYFUNCTION("""COMPUTED_VALUE"""),"editor") -> editor | E54: =IFERROR(__xludf.DUMMYFUNCTION("""COMPUTED_VALUE"""),"article") -> article | F54: =IFERROR(__xludf.DUMMYFUNCTION("""COMPUTED_VALUE"""),"network") -> network | H54: =VLOOKUP(B54,'new total list'!E:E,1,false) -> philip@mtsprout.nl | I54: =vlookup(A54,'new total list'!B:B,1,false) -> Philip Bueters | K54: =IF(AND(ISNA(H54), ISNA(I54)), "Marked", "")
A55: =IFERROR(__xludf.DUMMYFUNCTION("""COMPUTED_VALUE"""),"Rui Li") -> Rui Li | B55: =IFERROR(__xludf.DUMMYFUNCTION("""COMPUTED_VALUE"""),"rui.li@graduate.nl") -> rui.li@graduate.nl | C55: =IFERROR(__xludf.DUMMYFUNCTION("""COMPUTED_VALUE"""),"Graduate Ventures") -> Graduate Ventures | D55: =IFERROR(__xludf.DUMMYFUNCTION("""COMPUTED_VALUE"""),"Associate Principal") -> Associate Principal | E55: =IFERROR(__xludf.DUMMYFUNCTION("""COMPUTED_VALUE"""),"Reconnect with everyone") -> Reconnect with everyone | F55: =IFERROR(__xludf.DUMMYFUNCTION("""COMPUTED_VALUE"""),"meet new startups") -> meet new startups | H55: =VLOOKUP(B55,'new total list'!E:E,1,false) -> Rui.Li@graduate.nl | I55: =vlookup(A55,'new total list'!B:B,1,false) -> Rui Li | K55: =IF(AND(ISNA(H55), ISNA(I55)), "Marked", "")
A56: =IFERROR(__xludf.DUMMYFUNCTION("""COMPUTED_VALUE"""),"Dop") -> Dop | B56: =IFERROR(__xludf.DUMMYFUNCTION("""COMPUTED_VALUE"""),"dop.brzesowsky@gmail.com") -> dop.brzesowsky@gmail.com | C56: =IFERROR(__xludf.DUMMYFUNCTION("""COMPUTED_VALUE"""),"Berkenbosch Management") -> Berkenbosch Management | D56: =IFERROR(__xludf.DUMMYFUNCTION("""COMPUTED_VALUE"""),"Owner") -> Owner | E56: =IFERROR(__xludf.DUMMYFUNCTION("""COMPUTED_VALUE"""),"New ideas") -> New ideas | F56: =IFERROR(__xludf.DUMMYFUNCTION("""COMPUTED_VALUE"""),"MedTech") -> MedTech | H56: =VLOOKUP(B56,'new total list'!E:E,1,false) -> dop.brzesowsky@gmail.com | I56: =vlookup(A56,'new total list'!B:B,1,false) -> #N/A | K56: =IF(AND(ISNA(H56), ISNA(I56)), "Marked", "")
A57: =IFERROR(__xludf.DUMMYFUNCTION("""COMPUTED_VALUE"""),"Hidde Heimel") -> Hidde Heimel | B57: =IFERROR(__xludf.DUMMYFUNCTION("""COMPUTED_VALUE"""),"hheimel@8capital.nl") -> hheimel@8capital.nl | C57: =IFERROR(__xludf.DUMMYFUNCTION("""COMPUTED_VALUE"""),"8 Capital Group") -> 8 Capital Group | D57: =IFERROR(__xludf.DUMMYFUNCTION("""COMPUTED_VALUE"""),"Partner Investments") -> Partner Investments | E57: =IFERROR(__xludf.DUMMYFUNCTION("""COMPUTED_VALUE"""),"Meetinginteresting start ups / people to potenitally invest in") -> Meetinginteresting start ups / people to potenitally invest in | F57: =IFERROR(__xludf.DUMMYFUNCTION("""COMPUTED_VALUE"""),"Energy") -> Energy | H57: =VLOOKUP(B57,'new total list'!E:E,1,false) -> hheimel@8capital.nl | I57: =vlookup(A57,'new total list'!B:B,1,false) -> Hidde Heimel | K57: =IF(AND(ISNA(H57), ISNA(I57)), "Marked", "")
A58: =IFERROR(__xludf.DUMMYFUNCTION("""COMPUTED_VALUE"""),"Michiel van Stapele") -> Michiel van Stapele | B58: =IFERROR(__xludf.DUMMYFUNCTION("""COMPUTED_VALUE"""),"michiel.vanstapele@octrooicentrum.nl") -> michiel.vanstapele@octrooicentrum.nl | C58: =IFERROR(__xludf.DUMMYFUNCTION("""COMPUTED_VALUE"""),"Octrooicentrum Nederland / RVO") -> Octrooicentrum Nederland / RVO | D58: =IFERROR(__xludf.DUMMYFUNCTION("""COMPUTED_VALUE"""),"IP advisor") -> IP advisor | E58: =IFERROR(__xludf.DUMMYFUNCTION("""COMPUTED_VALUE"""),"IP awareness") -> IP awareness | F58: =IFERROR(__xludf.DUMMYFUNCTION("""COMPUTED_VALUE"""),"Energy") -> Energy | H58: =VLOOKUP(B58,'new total list'!E:E,1,false) -> michiel.vanstapele@octrooicentrum.nl | I58: =vlookup(A58,'new total list'!B:B,1,false) -> Michiel van Stapele | K58: =IF(AND(ISNA(H58), ISNA(I58)), "Marked", "")
A59: =IFERROR(__xludf.DUMMYFUNCTION("""COMPUTED_VALUE"""),"Gerko Visee") -> Gerko Visee | B59: =IFERROR(__xludf.DUMMYFUNCTION("""COMPUTED_VALUE"""),"gerko.visee@denhaag.nl") -> gerko.visee@denhaag.nl | C59: =IFERROR(__xludf.DUMMYFUNCTION("""COMPUTED_VALUE"""),"City of The Hague") -> City of The Hague | D59: =IFERROR(__xludf.DUMMYFUNCTION("""COMPUTED_VALUE"""),"Policy adviser international talent") -> Policy adviser international talent | E59: =IFERROR(__xludf.DUMMYFUNCTION("""COMPUTED_VALUE"""),"Network") -> Network | F59: =IFERROR(__xludf.DUMMYFUNCTION("""COMPUTED_VALUE"""),"​Aerospace") -> ​Aerospace | H59: =VLOOKUP(B59,'new total list'!E:E,1,false) -> gerko.visee@denhaag.nl | I59: =vlookup(A59,'new total list'!B:B,1,false) -> Gerko Visee | K59: =IF(AND(ISNA(H59), ISNA(I59)), "Marked", "")
A60: =IFERROR(__xludf.DUMMYFUNCTION("""COMPUTED_VALUE"""),"Rogier Barents") -> Rogier Barents | B60: =IFERROR(__xludf.DUMMYFUNCTION("""COMPUTED_VALUE"""),"rogier@intespring.nl") -> rogier@intespring.nl | C60: =IFERROR(__xludf.DUMMYFUNCTION("""COMPUTED_VALUE"""),"InteSpring") -> InteSpring | D60: =IFERROR(__xludf.DUMMYFUNCTION("""COMPUTED_VALUE"""),"Founder / CEO") -> Founder / CEO | E60: =IFERROR(__xludf.DUMMYFUNCTION("""COMPUTED_VALUE"""),"Contact with interesting defence startups") -> Contact with interesting defence startups | F60: =IFERROR(__xludf.DUMMYFUNCTION("""COMPUTED_VALUE"""),"Dual Use") -> Dual Use | H60: =VLOOKUP(B60,'new total list'!E:E,1,false) -> rogier@intespring.nl | I60: =vlookup(A60,'new total list'!B:B,1,false) -> Rogier Barents | K60: =IF(AND(ISNA(H60), ISNA(I60)), "Marked", "")
A61: =IFERROR(__xludf.DUMMYFUNCTION("""COMPUTED_VALUE"""),"Hugo Niezen") -> Hugo Niezen | B61: =IFERROR(__xludf.DUMMYFUNCTION("""COMPUTED_VALUE"""),"hugo.niezen@tno.nl") -> hugo.niezen@tno.nl | C61: =IFERROR(__xludf.DUMMYFUNCTION("""COMPUTED_VALUE"""),"TNO Fast Track") -> TNO Fast Track | D61: =IFERROR(__xludf.DUMMYFUNCTION("""COMPUTED_VALUE"""),"Senior Business Developer") -> Senior Business Developer | E61: =IFERROR(__xludf.DUMMYFUNCTION("""COMPUTED_VALUE"""),"Inspiration and relevant contacts") -> Inspiration and relevant contacts | F61: =IFERROR(__xludf.DUMMYFUNCTION("""COMPUTED_VALUE"""),"​Future of Compute") -> ​Future of Compute | H61: =VLOOKUP(B61,'new total list'!E:E,1,false) -> hugo.niezen@tno.nl | I61: =vlookup(A61,'new total list'!B:B,1,false) -> Hugo Niezen | K61: =IF(AND(ISNA(H61), ISNA(I61)), "Marked", "")
A62: =IFERROR(__xludf.DUMMYFUNCTION("""COMPUTED_VALUE"""),"Daniel Tajari") -> Daniel Tajari | B62: =IFERROR(__xludf.DUMMYFUNCTION("""COMPUTED_VALUE"""),"daniel.tajari@tno.nl") -> daniel.tajari@tno.nl | C62: =IFERROR(__xludf.DUMMYFUNCTION("""COMPUTED_VALUE"""),"Tno") -> Tno | D62: =IFERROR(__xludf.DUMMYFUNCTION("""COMPUTED_VALUE"""),"Project Manager") -> Project Manager | E62: =IFERROR(__xludf.DUMMYFUNCTION("""COMPUTED_VALUE"""),"Networking") -> Networking | F62: =IFERROR(__xludf.DUMMYFUNCTION("""COMPUTED_VALUE"""),"find potential startups for collaboration") -> find potential startups for collaboration | H62: =VLOOKUP(B62,'new total list'!E:E,1,false) -> #N/A | I62: =vlookup(A62,'new total list'!B:B,1,false) -> Daniel Tajari | K62: =IF(AND(ISNA(H62), ISNA(I62)), "Marked", "")
A63: =IFERROR(__xludf.DUMMYFUNCTION("""COMPUTED_VALUE"""),"Ralph van Dam") -> Ralph van Dam | B63: =IFERROR(__xludf.DUMMYFUNCTION("""COMPUTED_VALUE"""),"ralph.van.dam@achmea.nl") -> ralph.van.dam@achmea.nl | C63: =IFERROR(__xludf.DUMMYFUNCTION("""COMPUTED_VALUE"""),"Achmea Impact Ventures") -> Achmea Impact Ventures | D63: =IFERROR(__xludf.DUMMYFUNCTION("""COMPUTED_VALUE"""),"Head of Startups & Scaleups") -> Head of Startups & Scaleups | E63: =IFERROR(__xludf.DUMMYFUNCTION("""COMPUTED_VALUE"""),"Startup leads") -> Startup leads | F63: =IFERROR(__xludf.DUMMYFUNCTION("""COMPUTED_VALUE"""),"Energy") -> Energy | H63: =VLOOKUP(B63,'new total list'!E:E,1,false) -> ralph.van.dam@achmea.nl | I63: =vlookup(A63,'new total list'!B:B,1,false) -> Ralph Van Dam | K63: =IF(AND(ISNA(H63), ISNA(I63)), "Marked", "")
A64: =IFERROR(__xludf.DUMMYFUNCTION("""COMPUTED_VALUE"""),"Ton J. Jonker") -> Ton J. Jonker | B64: =IFERROR(__xludf.DUMMYFUNCTION("""COMPUTED_VALUE"""),"t.jonker@pzh.nl") -> t.jonker@pzh.nl | C64: =IFERROR(__xludf.DUMMYFUNCTION("""COMPUTED_VALUE"""),"PZH") -> PZH | D64: =IFERROR(__xludf.DUMMYFUNCTION("""COMPUTED_VALUE"""),"Director") -> Director | E64: =IFERROR(__xludf.DUMMYFUNCTION("""COMPUTED_VALUE"""),"Information") -> Information | F64: =IFERROR(__xludf.DUMMYFUNCTION("""COMPUTED_VALUE"""),"Energy") -> Energy | H64: =VLOOKUP(B64,'new total list'!E:E,1,false) -> t.jonker@pzh.nl | I64: =vlookup(A64,'new total list'!B:B,1,false) -> #N/A | K64: =IF(AND(ISNA(H64), ISNA(I64)), "Marked", "")
A65: =IFERROR(__xludf.DUMMYFUNCTION("""COMPUTED_VALUE"""),"Damien van der Bijl") -> Damien van der Bijl | B65: =IFERROR(__xludf.DUMMYFUNCTION("""COMPUTED_VALUE"""),"damien.vanderbijl@capricorn.be") -> damien.vanderbijl@capricorn.be | C65: =IFERROR(__xludf.DUMMYFUNCTION("""COMPUTED_VALUE"""),"Capricorn Partners") -> Capricorn Partners | D65: =IFERROR(__xludf.DUMMYFUNCTION("""COMPUTED_VALUE"""),"Investment Director") -> Investment Director | E65: =IFERROR(__xludf.DUMMYFUNCTION("""COMPUTED_VALUE"""),"Interesting leads") -> Interesting leads | F65: =IFERROR(__xludf.DUMMYFUNCTION("""COMPUTED_VALUE"""),"Energy") -> Energy | H65: =VLOOKUP(B65,'new total list'!E:E,1,false) -> damien.vanderbijl@capricorn.be | I65: =vlookup(A65,'new total list'!B:B,1,false) -> Damien van der Bijl | K65: =IF(AND(ISNA(H65), ISNA(I65)), "Marked", "")
A66: =IFERROR(__xludf.DUMMYFUNCTION("""COMPUTED_VALUE"""),"Stein") -> Stein | B66: =IFERROR(__xludf.DUMMYFUNCTION("""COMPUTED_VALUE"""),"steinar@hensk.es") -> steinar@hensk.es | C66: =IFERROR(__xludf.DUMMYFUNCTION("""COMPUTED_VALUE"""),"Bird Control Group") -> Bird Control Group | D66: =IFERROR(__xludf.DUMMYFUNCTION("""COMPUTED_VALUE"""),"Founder") -> Founder | E66: =IFERROR(__xludf.DUMMYFUNCTION("""COMPUTED_VALUE"""),"network") -> network | F66: =IFERROR(__xludf.DUMMYFUNCTION("""COMPUTED_VALUE"""),"Energy") -> Energy | H66: =VLOOKUP(B66,'new total list'!E:E,1,false) -> steinar@hensk.es | I66: =vlookup(A66,'new total list'!B:B,1,false) -> #N/A | K66: =IF(AND(ISNA(H66), ISNA(I66)), "Marked", "")
A67: =IFERROR(__xludf.DUMMYFUNCTION("""COMPUTED_VALUE"""),"Robert Huijsmans") -> Robert Huijsmans | B67: =IFERROR(__xludf.DUMMYFUNCTION("""COMPUTED_VALUE"""),"rhuijsmans@ipcentric.nl") -> rhuijsmans@ipcentric.nl | C67: =IFERROR(__xludf.DUMMYFUNCTION("""COMPUTED_VALUE"""),"IPCentric Solutions") -> IPCentric Solutions | D67: =IFERROR(__xludf.DUMMYFUNCTION("""COMPUTED_VALUE"""),"Founder") -> Founder | E67: =IFERROR(__xludf.DUMMYFUNCTION("""COMPUTED_VALUE"""),"Networking") -> Networking | F67: =IFERROR(__xludf.DUMMYFUNCTION("""COMPUTED_VALUE"""),"Cyber") -> Cyber | H67: =VLOOKUP(B67,'new total list'!E:E,1,false) -> rhuijsmans@ipcentric.nl | I67: =vlookup(A67,'new total list'!B:B,1,false) -> #N/A | K67: =IF(AND(ISNA(H67), ISNA(I67)), "Marked", "")
A68: =IFERROR(__xludf.DUMMYFUNCTION("""COMPUTED_VALUE"""),"Nick Bos") -> Nick Bos | B68: =IFERROR(__xludf.DUMMYFUNCTION("""COMPUTED_VALUE"""),"n.j.p.m.bos@tudelft.nl") -> n.j.p.m.bos@tudelft.nl | C68: =IFERROR(__xludf.DUMMYFUNCTION("""COMPUTED_VALUE"""),"TU Delft College van Bestuur") -> TU Delft College van Bestuur | D68: =IFERROR(__xludf.DUMMYFUNCTION("""COMPUTED_VALUE"""),"CvB-lid Portefeuillehouder Bedrijfsvoering") -> CvB-lid Portefeuillehouder Bedrijfsvoering | E68: =IFERROR(__xludf.DUMMYFUNCTION("""COMPUTED_VALUE"""),"Kennis") -> Kennis | F68: =IFERROR(__xludf.DUMMYFUNCTION("""COMPUTED_VALUE"""),"Energy") -> Energy | H68: =VLOOKUP(B68,'new total list'!E:E,1,false) -> n.j.p.m.bos@tudelft.nl | I68: =vlookup(A68,'new total list'!B:B,1,false) -> Nick Bos | K68: =IF(AND(ISNA(H68), ISNA(I68)), "Marked", "")
A69: =IFERROR(__xludf.DUMMYFUNCTION("""COMPUTED_VALUE"""),"Vareska van de Vrande") -> Vareska van de Vrande | B69: =IFERROR(__xludf.DUMMYFUNCTION("""COMPUTED_VALUE"""),"vvrande@rsm.nl") -> vvrande@rsm.nl | C69: =IFERROR(__xludf.DUMMYFUNCTION("""COMPUTED_VALUE"""),"Rotterdam School of Management") -> Rotterdam School of Management | D69: =IFERROR(__xludf.DUMMYFUNCTION("""COMPUTED_VALUE"""),"Erasmus University") -> Erasmus University | E69: =IFERROR(__xludf.DUMMYFUNCTION("""COMPUTED_VALUE"""),"Professor of Collaborative Innovation and Business Venturing") -> Professor of Collaborative Innovation and Business Venturing | F69: =IFERROR(__xludf.DUMMYFUNCTION("""COMPUTED_VALUE"""),"Networking") -> Networking | H69: =VLOOKUP(B69,'new total list'!E:E,1,false) -> vvrande@rsm.nl | I69: =vlookup(A69,'new total list'!B:B,1,false) -> Vareska van de Vrande | K69: =IF(AND(ISNA(H69), ISNA(I69)), "Marked", "")
A70: =IFERROR(__xludf.DUMMYFUNCTION("""COMPUTED_VALUE"""),"Diana Droog") -> Diana Droog | B70: =IFERROR(__xludf.DUMMYFUNCTION("""COMPUTED_VALUE"""),"d.droog@tudelft.nl") -> d.droog@tudelft.nl | C70: =IFERROR(__xludf.DUMMYFUNCTION("""COMPUTED_VALUE"""),"TU Delft") -> TU Delft | D70: =IFERROR(__xludf.DUMMYFUNCTION("""COMPUTED_VALUE"""),"EU Funding support - NATO DIANA Support") -> EU Funding support - NATO DIANA Support | E70: =IFERROR(__xludf.DUMMYFUNCTION("""COMPUTED_VALUE"""),"to widingen my netwerk") -> to widingen my netwerk | F70: =IFERROR(__xludf.DUMMYFUNCTION("""COMPUTED_VALUE"""),"Dual Use") -> Dual Use | H70: =VLOOKUP(B70,'new total list'!E:E,1,false) -> d.droog@tudelft.nl | I70: =vlookup(A70,'new total list'!B:B,1,false) -> Diana Droog | K70: =IF(AND(ISNA(H70), ISNA(I70)), "Marked", "")
A71: =IFERROR(__xludf.DUMMYFUNCTION("""COMPUTED_VALUE"""),"Arie Slottje") -> Arie Slottje | B71: =IFERROR(__xludf.DUMMYFUNCTION("""COMPUTED_VALUE"""),"slottjearie@gmail.com") -> slottjearie@gmail.com | C71: =IFERROR(__xludf.DUMMYFUNCTION("""COMPUTED_VALUE"""),"Na") -> Na | D71: =IFERROR(__xludf.DUMMYFUNCTION("""COMPUTED_VALUE"""),"YES!Delft mentor") -> YES!Delft mentor | E71: =IFERROR(__xludf.DUMMYFUNCTION("""COMPUTED_VALUE"""),"Contacts and inspiration") -> Contacts and inspiration | F71: =IFERROR(__xludf.DUMMYFUNCTION("""COMPUTED_VALUE"""),"MedTech") -> MedTech | H71: =VLOOKUP(B71,'new total list'!E:E,1,false) -> slottjearie@gmail.com | I71: =vlookup(A71,'new total list'!B:B,1,false) -> Arie Slottje | K71: =IF(AND(ISNA(H71), ISNA(I71)), "Marked", "")
A72: =IFERROR(__xludf.DUMMYFUNCTION("""COMPUTED_VALUE"""),"Sven Bakkes") -> Sven Bakkes | B72: =IFERROR(__xludf.DUMMYFUNCTION("""COMPUTED_VALUE"""),"sven@lumolabs.io") -> sven@lumolabs.io | C72: =IFERROR(__xludf.DUMMYFUNCTION("""COMPUTED_VALUE"""),"LUMO Labs") -> LUMO Labs | D72: =IFERROR(__xludf.DUMMYFUNCTION("""COMPUTED_VALUE"""),"Founding Partner") -> Founding Partner | E72: =IFERROR(__xludf.DUMMYFUNCTION("""COMPUTED_VALUE"""),"Netwerken") -> Netwerken | F72: =IFERROR(__xludf.DUMMYFUNCTION("""COMPUTED_VALUE"""),"MedTech") -> MedTech | H72: =VLOOKUP(B72,'new total list'!E:E,1,false) -> sven@lumolabs.io | I72: =vlookup(A72,'new total list'!B:B,1,false) -> Sven Bakkes | K72: =IF(AND(ISNA(H72), ISNA(I72)), "Marked", "") | L72: OK FS
A73: =IFERROR(__xludf.DUMMYFUNCTION("""COMPUTED_VALUE"""),"Ronald Gelderblom") -> Ronald Gelderblom | B73: =IFERROR(__xludf.DUMMYFUNCTION("""COMPUTED_VALUE"""),"r.gelderblom@tudelft.nl") -> r.gelderblom@tudelft.nl | C73: =IFERROR(__xludf.DUMMYFUNCTION("""COMPUTED_VALUE"""),"Delft Enterprises") -> Delft Enterprises | D73: =IFERROR(__xludf.DUMMYFUNCTION("""COMPUTED_VALUE"""),"Managing Director") -> Managing Director | E73: =IFERROR(__xludf.DUMMYFUNCTION("""COMPUTED_VALUE"""),"Networking") -> Networking | F73: =IFERROR(__xludf.DUMMYFUNCTION("""COMPUTED_VALUE"""),"​Future of Compute") -> ​Future of Compute | H73: =VLOOKUP(B73,'new total list'!E:E,1,false) -> R.Gelderblom@tudelft.nl | I73: =vlookup(A73,'new total list'!B:B,1,false) -> Ronald Gelderblom | K73: =IF(AND(ISNA(H73), ISNA(I73)), "Marked", "")
A74: =IFERROR(__xludf.DUMMYFUNCTION("""COMPUTED_VALUE"""),"Erik Ver") -> Erik Ver | B74: =IFERROR(__xludf.DUMMYFUNCTION("""COMPUTED_VALUE"""),"verloopbv@hotmail.com") -> verloopbv@hotmail.com | C74: =IFERROR(__xludf.DUMMYFUNCTION("""COMPUTED_VALUE"""),"Verloop Solutions BV") -> Verloop Solutions BV | D74: =IFERROR(__xludf.DUMMYFUNCTION("""COMPUTED_VALUE"""),"Directeur") -> Directeur | E74: =IFERROR(__xludf.DUMMYFUNCTION("""COMPUTED_VALUE"""),"Meet up with founders") -> Meet up with founders | F74: =IFERROR(__xludf.DUMMYFUNCTION("""COMPUTED_VALUE"""),"Maritime") -> Maritime | H74: =VLOOKUP(B74,'new total list'!E:E,1,false) -> verloopbv@hotmail.com | I74: =vlookup(A74,'new total list'!B:B,1,false) -> #N/A | K74: =IF(AND(ISNA(H74), ISNA(I74)), "Marked", "") | L74: OK, jg
A75: =IFERROR(__xludf.DUMMYFUNCTION("""COMPUTED_VALUE"""),"Stef Prinsen") -> Stef Prinsen | B75: =IFERROR(__xludf.DUMMYFUNCTION("""COMPUTED_VALUE"""),"stef.prinsen@tno.nl") -> stef.prinsen@tno.nl | C75: =IFERROR(__xludf.DUMMYFUNCTION("""COMPUTED_VALUE"""),"TNO Fast Track") -> TNO Fast Track | D75: =IFERROR(__xludf.DUMMYFUNCTION("""COMPUTED_VALUE"""),"Business Developer") -> Business Developer | E75: =IFERROR(__xludf.DUMMYFUNCTION("""COMPUTED_VALUE"""),"Our mission is to accelerate the R&D roadmap of Dutch deeptech startups. Always keen to speak with founders and hear about their technical challanges and ambitions") -> Our mission is to accelerate the R&D roadmap of Dutch deeptech startups. Always keen to speak with founders and hear about their technical challanges and ambitions | F75: =IFERROR(__xludf.DUMMYFUNCTION("""COMPUTED_VALUE"""),"Energy") -> Energy | H75: =VLOOKUP(B75,'new total list'!E:E,1,false) -> stef.prinsen@tno.nl | I75: =vlookup(A75,'new total list'!B:B,1,false) -> Stef Prinsen | K75: =IF(AND(ISNA(H75), ISNA(I75)), "Marked", "") | L75: OK, jg
A76: =IFERROR(__xludf.DUMMYFUNCTION("""COMPUTED_VALUE"""),"Frederik Westerouen van Meeteren") -> Frederik Westerouen van Meeteren | B76: =IFERROR(__xludf.DUMMYFUNCTION("""COMPUTED_VALUE"""),"fvanmeeteren@gmail.com") -> fvanmeeteren@gmail.com | C76: =IFERROR(__xludf.DUMMYFUNCTION("""COMPUTED_VALUE"""),"FWVM Enterprises B.V.") -> FWVM Enterprises B.V. | D76: =IFERROR(__xludf.DUMMYFUNCTION("""COMPUTED_VALUE"""),"Innovation Strategist & Startup Mentor") -> Innovation Strategist & Startup Mentor | E76: =IFERROR(__xludf.DUMMYFUNCTION("""COMPUTED_VALUE"""),"Help startups grow to the next level!") -> Help startups grow to the next level! | F76: =IFERROR(__xludf.DUMMYFUNCTION("""COMPUTED_VALUE"""),"​Future of Compute") -> ​Future of Compute | H76: =VLOOKUP(B76,'new total list'!E:E,1,false) -> fvanmeeteren@gmail.com | I76: =vlookup(A76,'new total list'!B:B,1,false) -> Frederik Westerouen van Meeteren | K76: =IF(AND(ISNA(H76), ISNA(I76)), "Marked", "")
A77: =IFERROR(__xludf.DUMMYFUNCTION("""COMPUTED_VALUE"""),"Floris Van Den Broek") -> Floris Van Den Broek | B77: =IFERROR(__xludf.DUMMYFUNCTION("""COMPUTED_VALUE"""),"floris@ictinstitute.nl") -> floris@ictinstitute.nl | C77: =IFERROR(__xludf.DUMMYFUNCTION("""COMPUTED_VALUE"""),"ict institute") -> ict institute | D77: =IFERROR(__xludf.DUMMYFUNCTION("""COMPUTED_VALUE"""),"partner") -> partner | E77: =IFERROR(__xludf.DUMMYFUNCTION("""COMPUTED_VALUE"""),"network") -> network | F77: =IFERROR(__xludf.DUMMYFUNCTION("""COMPUTED_VALUE"""),"Cyber") -> Cyber | H77: =VLOOKUP(B77,'new total list'!E:E,1,false) -> #N/A | I77: =vlookup(A77,'new total list'!B:B,1,false) -> Floris van den Broek | K77: =IF(AND(ISNA(H77), ISNA(I77)), "Marked", "")
A78: =IFERROR(__xludf.DUMMYFUNCTION("""COMPUTED_VALUE"""),"Cas van Cooten") -> Cas van Cooten | B78: =IFERROR(__xludf.DUMMYFUNCTION("""COMPUTED_VALUE"""),"cas@offensys.com") -> cas@offensys.com | C78: =IFERROR(__xludf.DUMMYFUNCTION("""COMPUTED_VALUE"""),"Offensys") -> Offensys | D78: =IFERROR(__xludf.DUMMYFUNCTION("""COMPUTED_VALUE"""),"Co-founder") -> Co-founder | E78: =IFERROR(__xludf.DUMMYFUNCTION("""COMPUTED_VALUE"""),"Exposure for startup (booth and/or pitches)") -> Exposure for startup (booth and/or pitches) | F78: =IFERROR(__xludf.DUMMYFUNCTION("""COMPUTED_VALUE"""),"networking") -> networking | H78: =VLOOKUP(B78,'new total list'!E:E,1,false) -> #N/A | I78: =vlookup(A78,'new total list'!B:B,1,false) -> Cas van Cooten | K78: =IF(AND(ISNA(H78), ISNA(I78)), "Marked", "")
A79: =IFERROR(__xludf.DUMMYFUNCTION("""COMPUTED_VALUE"""),"Frank Schuijer") -> Frank Schuijer | B79: =IFERROR(__xludf.DUMMYFUNCTION("""COMPUTED_VALUE"""),"frank@sirrom.nl") -> frank@sirrom.nl | C79: =IFERROR(__xludf.DUMMYFUNCTION("""COMPUTED_VALUE"""),"Sirrom Holding B.V.") -> Sirrom Holding B.V. | D79: =IFERROR(__xludf.DUMMYFUNCTION("""COMPUTED_VALUE"""),"Startup mentor") -> Startup mentor | E79: =IFERROR(__xludf.DUMMYFUNCTION("""COMPUTED_VALUE"""),"Getting more excited about our ecosystem") -> Getting more excited about our ecosystem | F79: =IFERROR(__xludf.DUMMYFUNCTION("""COMPUTED_VALUE"""),"Dual Use") -> Dual Use | H79: =VLOOKUP(B79,'new total list'!E:E,1,false) -> frank@sirrom.nl | I79: =vlookup(A79,'new total list'!B:B,1,false) -> Frank Schuijer | K79: =IF(AND(ISNA(H79), ISNA(I79)), "Marked", "")
A80: =IFERROR(__xludf.DUMMYFUNCTION("""COMPUTED_VALUE"""),"Vlado") -> Vlado | B80: =IFERROR(__xludf.DUMMYFUNCTION("""COMPUTED_VALUE"""),"vlado@synemedia.eu") -> vlado@synemedia.eu | C80: =IFERROR(__xludf.DUMMYFUNCTION("""COMPUTED_VALUE"""),"Synemedia") -> Synemedia | D80: =IFERROR(__xludf.DUMMYFUNCTION("""COMPUTED_VALUE"""),"Owner") -> Owner | E80: =IFERROR(__xludf.DUMMYFUNCTION("""COMPUTED_VALUE"""),"Meet teams to work with") -> Meet teams to work with | F80: =IFERROR(__xludf.DUMMYFUNCTION("""COMPUTED_VALUE"""),"MedTech") -> MedTech | H80: =VLOOKUP(B80,'new total list'!E:E,1,false) -> #N/A | I80: =vlookup(A80,'new total list'!B:B,1,false) -> #N/A | K80: =IF(AND(ISNA(H80), ISNA(I80)), "Marked", "") -> Marked
A81: =IFERROR(__xludf.DUMMYFUNCTION("""COMPUTED_VALUE"""),"Richard Holleman") -> Richard Holleman | B81: =IFERROR(__xludf.DUMMYFUNCTION("""COMPUTED_VALUE"""),"richard@caricecars.com") -> richard@caricecars.com | C81: =IFERROR(__xludf.DUMMYFUNCTION("""COMPUTED_VALUE"""),"Carice BV") -> Carice BV | D81: =IFERROR(__xludf.DUMMYFUNCTION("""COMPUTED_VALUE"""),"Founder") -> Founder | E81: =IFERROR(__xludf.DUMMYFUNCTION("""COMPUTED_VALUE"""),"Making friends to make the world a little nicer.") -> Making friends to make the world a little nicer. | F81: =IFERROR(__xludf.DUMMYFUNCTION("""COMPUTED_VALUE"""),"Energy") -> Energy | H81: =VLOOKUP(B81,'new total list'!E:E,1,false) -> richard@caricecars.com | I81: =vlookup(A81,'new total list'!B:B,1,false) -> Richard Holleman | K81: =IF(AND(ISNA(H81), ISNA(I81)), "Marked", "")
A82: =IFERROR(__xludf.DUMMYFUNCTION("""COMPUTED_VALUE"""),"Flip Jansen") -> Flip Jansen | B82: =IFERROR(__xludf.DUMMYFUNCTION("""COMPUTED_VALUE"""),"fj@innovationindustries.com") -> fj@innovationindustries.com | C82: =IFERROR(__xludf.DUMMYFUNCTION("""COMPUTED_VALUE"""),"Innovation Industries") -> Innovation Industries | D82: =IFERROR(__xludf.DUMMYFUNCTION("""COMPUTED_VALUE"""),"Investment Analyst") -> Investment Analyst | E82: =IFERROR(__xludf.DUMMYFUNCTION("""COMPUTED_VALUE"""),"Network and sourcing") -> Network and sourcing | F82: =IFERROR(__xludf.DUMMYFUNCTION("""COMPUTED_VALUE"""),"​Future of Compute") -> ​Future of Compute | H82: =VLOOKUP(B82,'new total list'!E:E,1,false) -> #N/A | I82: =vlookup(A82,'new total list'!B:B,1,false) -> #N/A | K82: =IF(AND(ISNA(H82), ISNA(I82)), "Marked", "") -> Marked
A83: =IFERROR(__xludf.DUMMYFUNCTION("""COMPUTED_VALUE"""),"Patrick Besten") -> Patrick Besten | B83: =IFERROR(__xludf.DUMMYFUNCTION("""COMPUTED_VALUE"""),"p.j.besten@icloud.com") -> p.j.besten@icloud.com | C83: =IFERROR(__xludf.DUMMYFUNCTION("""COMPUTED_VALUE"""),"Flywheel Impact") -> Flywheel Impact | D83: =IFERROR(__xludf.DUMMYFUNCTION("""COMPUTED_VALUE"""),"DGA") -> DGA | E83: =IFERROR(__xludf.DUMMYFUNCTION("""COMPUTED_VALUE"""),"possible leads") -> possible leads | F83: =IFERROR(__xludf.DUMMYFUNCTION("""COMPUTED_VALUE"""),"Maritime") -> Maritime | H83: =VLOOKUP(B83,'new total list'!E:E,1,false) -> #N/A | I83: =vlookup(A83,'new total list'!B:B,1,false) -> #N/A | K83: =IF(AND(ISNA(H83), ISNA(I83)), "Marked", "") -> Marked
A84: =IFERROR(__xludf.DUMMYFUNCTION("""COMPUTED_VALUE"""),"Salima Oualite") -> Salima Oualite | B84: =IFERROR(__xludf.DUMMYFUNCTION("""COMPUTED_VALUE"""),"salima.oualite@denhaag.nl") -> salima.oualite@denhaag.nl | C84: =IFERROR(__xludf.DUMMYFUNCTION("""COMPUTED_VALUE"""),"The Hague Municipality") -> The Hague Municipality | D84: =IFERROR(__xludf.DUMMYFUNCTION("""COMPUTED_VALUE"""),"Policy Advisor Economic Affairs") -> Policy Advisor Economic Affairs | E84: =IFERROR(__xludf.DUMMYFUNCTION("""COMPUTED_VALUE"""),"Insight into innovations and developments within the ecosystem and its networks") -> Insight into innovations and developments within the ecosystem and its networks | F84: =IFERROR(__xludf.DUMMYFUNCTION("""COMPUTED_VALUE"""),"Maritime") -> Maritime | H84: =VLOOKUP(B84,'new total list'!E:E,1,false) -> salima.oualite@denhaag.nl | I84: =vlookup(A84,'new total list'!B:B,1,false) -> Salima Oualite | K84: =IF(AND(ISNA(H84), ISNA(I84)), "Marked", "")
A85: =IFERROR(__xludf.DUMMYFUNCTION("""COMPUTED_VALUE"""),"Ellen Hensbergen") -> Ellen Hensbergen | B85: =IFERROR(__xludf.DUMMYFUNCTION("""COMPUTED_VALUE"""),"ellen.hensbergen@invesdor.com") -> ellen.hensbergen@invesdor.com | C85: =IFERROR(__xludf.DUMMYFUNCTION("""COMPUTED_VALUE"""),"Invesdor") -> Invesdor | D85: =IFERROR(__xludf.DUMMYFUNCTION("""COMPUTED_VALUE"""),"Managing Director") -> Managing Director | E85: =IFERROR(__xludf.DUMMYFUNCTION("""COMPUTED_VALUE"""),"Get to know new companies") -> Get to know new companies | F85: =IFERROR(__xludf.DUMMYFUNCTION("""COMPUTED_VALUE"""),"Energy") -> Energy | H85: =VLOOKUP(B85,'new total list'!E:E,1,false) -> ellen.hensbergen@invesdor.com | I85: =vlookup(A85,'new total list'!B:B,1,false) -> Ellen Hensbergen | K85: =IF(AND(ISNA(H85), ISNA(I85)), "Marked", "")
A86: =IFERROR(__xludf.DUMMYFUNCTION("""COMPUTED_VALUE"""),"Ralf") -> Ralf | B86: =IFERROR(__xludf.DUMMYFUNCTION("""COMPUTED_VALUE"""),"ralf@ralfheijkants.nl") -> ralf@ralfheijkants.nl | C86: =IFERROR(__xludf.DUMMYFUNCTION("""COMPUTED_VALUE"""),"heijkants") -> heijkants | D86: =IFERROR(__xludf.DUMMYFUNCTION("""COMPUTED_VALUE"""),"consulant") -> consulant | E86: =IFERROR(__xludf.DUMMYFUNCTION("""COMPUTED_VALUE"""),"finding startup to join as co-founder") -> finding startup to join as co-founder | F86: =IFERROR(__xludf.DUMMYFUNCTION("""COMPUTED_VALUE"""),"MedTech") -> MedTech | H86: =VLOOKUP(B86,'new total list'!E:E,1,false) -> ralf@ralfheijkants.nl | I86: =vlookup(A86,'new total list'!B:B,1,false) -> #N/A | K86: =IF(AND(ISNA(H86), ISNA(I86)), "Marked", "")
A87: =IFERROR(__xludf.DUMMYFUNCTION("""COMPUTED_VALUE"""),"tamas puski") -> tamas puski | B87: =IFERROR(__xludf.DUMMYFUNCTION("""COMPUTED_VALUE"""),"puskitamas@gmail.com") -> puskitamas@gmail.com | C87: =IFERROR(__xludf.DUMMYFUNCTION("""COMPUTED_VALUE"""),"iseeq") -> iseeq | D87: =IFERROR(__xludf.DUMMYFUNCTION("""COMPUTED_VALUE"""),"md") -> md | E87: =IFERROR(__xludf.DUMMYFUNCTION("""COMPUTED_VALUE"""),"networking") -> networking | F87: =IFERROR(__xludf.DUMMYFUNCTION("""COMPUTED_VALUE"""),"Dual Use") -> Dual Use | H87: =VLOOKUP(B87,'new total list'!E:E,1,false) -> #N/A | I87: =vlookup(A87,'new total list'!B:B,1,false) -> Tamas Puski | K87: =IF(AND(ISNA(H87), ISNA(I87)), "Marked", "")
A88: =IFERROR(__xludf.DUMMYFUNCTION("""COMPUTED_VALUE"""),"Rens Schoenmakers") -> Rens Schoenmakers | B88: =IFERROR(__xludf.DUMMYFUNCTION("""COMPUTED_VALUE"""),"rens@fyeo.nl") -> rens@fyeo.nl | C88: =IFERROR(__xludf.DUMMYFUNCTION("""COMPUTED_VALUE"""),"FYEO") -> FYEO | D88: =IFERROR(__xludf.DUMMYFUNCTION("""COMPUTED_VALUE"""),"CEO") -> CEO | E88: =IFERROR(__xludf.DUMMYFUNCTION("""COMPUTED_VALUE"""),"meet startups and support the ones I have been mentoring") -> meet startups and support the ones I have been mentoring | F88: =IFERROR(__xludf.DUMMYFUNCTION("""COMPUTED_VALUE"""),"MedTech") -> MedTech | H88: =VLOOKUP(B88,'new total list'!E:E,1,false) -> rens@fyeo.nl | I88: =vlookup(A88,'new total list'!B:B,1,false) -> Rens Schoenmakers | K88: =IF(AND(ISNA(H88), ISNA(I88)), "Marked", "")
A89: =IFERROR(__xludf.DUMMYFUNCTION("""COMPUTED_VALUE"""),"Auke van den Hout") -> Auke van den Hout | B89: =IFERROR(__xludf.DUMMYFUNCTION("""COMPUTED_VALUE"""),"auke.vandenhout@graduate.nl") -> auke.vandenhout@graduate.nl | C89: =IFERROR(__xludf.DUMMYFUNCTION("""COMPUTED_VALUE"""),"Graduate Ventures") -> Graduate Ventures | D89: =IFERROR(__xludf.DUMMYFUNCTION("""COMPUTED_VALUE"""),"Managing Partner") -> Managing Partner | E89: =IFERROR(__xludf.DUMMYFUNCTION("""COMPUTED_VALUE"""),"Start uops") -> Start uops | F89: =IFERROR(__xludf.DUMMYFUNCTION("""COMPUTED_VALUE"""),"Energy") -> Energy | H89: =VLOOKUP(B89,'new total list'!E:E,1,false) -> auke.vandenhout@graduate.nl | I89: =vlookup(A89,'new total list'!B:B,1,false) -> Auke van den Hout | K89: =IF(AND(ISNA(H89), ISNA(I89)), "Marked", "")
A90: =IFERROR(__xludf.DUMMYFUNCTION("""COMPUTED_VALUE"""),"Dan Veen") -> Dan Veen | B90: =IFERROR(__xludf.DUMMYFUNCTION("""COMPUTED_VALUE"""),"veen@maritimeoffshore.nl") -> veen@maritimeoffshore.nl | C90: =IFERROR(__xludf.DUMMYFUNCTION("""COMPUTED_VALUE"""),"Maritime & Offshore NL") -> Maritime & Offshore NL | D90: =IFERROR(__xludf.DUMMYFUNCTION("""COMPUTED_VALUE"""),"Team Lead") -> Team Lead | E90: =IFERROR(__xludf.DUMMYFUNCTION("""COMPUTED_VALUE"""),"Acces to maritime startups") -> Acces to maritime startups | F90: =IFERROR(__xludf.DUMMYFUNCTION("""COMPUTED_VALUE"""),"Maritime") -> Maritime | H90: =VLOOKUP(B90,'new total list'!E:E,1,false) -> #N/A | I90: =vlookup(A90,'new total list'!B:B,1,false) -> Dan Veen | K90: =IF(AND(ISNA(H90), ISNA(I90)), "Marked", "")
A91: =IFERROR(__xludf.DUMMYFUNCTION("""COMPUTED_VALUE"""),"Rutger Arisz") -> Rutger Arisz | B91: =IFERROR(__xludf.DUMMYFUNCTION("""COMPUTED_VALUE"""),"rutger.arisz@gmail.com") -> rutger.arisz@gmail.com | C91: =IFERROR(__xludf.DUMMYFUNCTION("""COMPUTED_VALUE"""),"ARISZ Management & Consultancy") -> ARISZ Management & Consultancy | D91: =IFERROR(__xludf.DUMMYFUNCTION("""COMPUTED_VALUE"""),"CEO") -> CEO | E91: =IFERROR(__xludf.DUMMYFUNCTION("""COMPUTED_VALUE"""),"Network rejuvination") -> Network rejuvination | F91: =IFERROR(__xludf.DUMMYFUNCTION("""COMPUTED_VALUE"""),"MedTech") -> MedTech | H91: =VLOOKUP(B91,'new total list'!E:E,1,false) -> rutger.arisz@gmail.com | I91: =vlookup(A91,'new total list'!B:B,1,false) -> Rutger Arisz | K91: =IF(AND(ISNA(H91), ISNA(I91)), "Marked", "")
A92: =IFERROR(__xludf.DUMMYFUNCTION("""COMPUTED_VALUE"""),"Régis Cazenave") -> Régis Cazenave | B92: =IFERROR(__xludf.DUMMYFUNCTION("""COMPUTED_VALUE"""),"regis@mindforward.eu") -> regis@mindforward.eu | C92: =IFERROR(__xludf.DUMMYFUNCTION("""COMPUTED_VALUE"""),"Mind Forward") -> Mind Forward | D92: =IFERROR(__xludf.DUMMYFUNCTION("""COMPUTED_VALUE"""),"Managing Partner") -> Managing Partner | E92: =IFERROR(__xludf.DUMMYFUNCTION("""COMPUTED_VALUE"""),"Meet the Startups to exchange ideas") -> Meet the Startups to exchange ideas | F92: =IFERROR(__xludf.DUMMYFUNCTION("""COMPUTED_VALUE"""),"explore collaboration opportunities") -> explore collaboration opportunities | H92: =VLOOKUP(B92,'new total list'!E:E,1,false) -> regis@mindforward.eu | I92: =vlookup(A92,'new total list'!B:B,1,false) -> Régis Cazenave | K92: =IF(AND(ISNA(H92), ISNA(I92)), "Marked", "")
A93: =IFERROR(__xludf.DUMMYFUNCTION("""COMPUTED_VALUE"""),"Moritz Mueller") -> Moritz Mueller | B93: =IFERROR(__xludf.DUMMYFUNCTION("""COMPUTED_VALUE"""),"moritzmueller@setventures.com") -> moritzmueller@setventures.com | C93: =IFERROR(__xludf.DUMMYFUNCTION("""COMPUTED_VALUE"""),"SET Ventures") -> SET Ventures | D93: =IFERROR(__xludf.DUMMYFUNCTION("""COMPUTED_VALUE"""),"Investment Manager") -> Investment Manager | E93: =IFERROR(__xludf.DUMMYFUNCTION("""COMPUTED_VALUE"""),"Meet energy start-ups and get to know the ecosystem.") -> Meet energy start-ups and get to know the ecosystem. | F93: =IFERROR(__xludf.DUMMYFUNCTION("""COMPUTED_VALUE"""),"Energy") -> Energy | H93: =VLOOKUP(B93,'new total list'!E:E,1,false) -> moritzmueller@setventures.com | I93: =vlookup(A93,'new total list'!B:B,1,false) -> #N/A | K93: =IF(AND(ISNA(H93), ISNA(I93)), "Marked", "")
A94: =IFERROR(__xludf.DUMMYFUNCTION("""COMPUTED_VALUE"""),"Ken Gould") -> Ken Gould | B94: =IFERROR(__xludf.DUMMYFUNCTION("""COMPUTED_VALUE"""),"gould@evamobility.org") -> gould@evamobility.org | C94: =IFERROR(__xludf.DUMMYFUNCTION("""COMPUTED_VALUE"""),"EVA") -> EVA | D94: =IFERROR(__xludf.DUMMYFUNCTION("""COMPUTED_VALUE"""),"Founder") -> Founder | E94: =IFERROR(__xludf.DUMMYFUNCTION("""COMPUTED_VALUE"""),"Inspiration") -> Inspiration | F94: =IFERROR(__xludf.DUMMYFUNCTION("""COMPUTED_VALUE"""),"Energy") -> Energy | H94: =VLOOKUP(B94,'new total list'!E:E,1,false) -> #N/A | I94: =vlookup(A94,'new total list'!B:B,1,false) -> Ken Gould | K94: =IF(AND(ISNA(H94), ISNA(I94)), "Marked", "") | L94: ok, jg
A95: =IFERROR(__xludf.DUMMYFUNCTION("""COMPUTED_VALUE"""),"Hendrik Verschuur") -> Hendrik Verschuur | B95: =IFERROR(__xludf.DUMMYFUNCTION("""COMPUTED_VALUE"""),"hpverwchuur@gmail.com") -> hpverwchuur@gmail.com | C95: =IFERROR(__xludf.DUMMYFUNCTION("""COMPUTED_VALUE"""),"I’m a mentor") -> I’m a mentor | D95: =IFERROR(__xludf.DUMMYFUNCTION("""COMPUTED_VALUE"""),"Doctor") -> Doctor | E95: =IFERROR(__xludf.DUMMYFUNCTION("""COMPUTED_VALUE"""),"Mentoring") -> Mentoring | F95: =IFERROR(__xludf.DUMMYFUNCTION("""COMPUTED_VALUE"""),"MedTech") -> MedTech | H95: =VLOOKUP(B95,'new total list'!E:E,1,false) -> #N/A | I95: =vlookup(A95,'new total list'!B:B,1,false) -> Hendrik Verschuur | K95: =IF(AND(ISNA(H95), ISNA(I95)), "Marked", "")
A96: =IFERROR(__xludf.DUMMYFUNCTION("""COMPUTED_VALUE"""),"Matthew Burton") -> Matthew Burton | B96: =IFERROR(__xludf.DUMMYFUNCTION("""COMPUTED_VALUE"""),"matt@mfbconsulting.nl") -> matt@mfbconsulting.nl | C96: =IFERROR(__xludf.DUMMYFUNCTION("""COMPUTED_VALUE"""),"MFB Consulting BV") -> MFB Consulting BV | D96: =IFERROR(__xludf.DUMMYFUNCTION("""COMPUTED_VALUE"""),"Patent Attorney / Innovation & IP Consultant") -> Patent Attorney / Innovation & IP Consultant | E96: =IFERROR(__xludf.DUMMYFUNCTION("""COMPUTED_VALUE"""),"meet exciting young companies; meet companies looking for innovation/IP/patent support") -> meet exciting young companies; meet companies looking for innovation/IP/patent support | F96: =IFERROR(__xludf.DUMMYFUNCTION("""COMPUTED_VALUE"""),"Energy") -> Energy | H96: =VLOOKUP(B96,'new total list'!E:E,1,false) -> matt@mfbconsulting.nl | I96: =vlookup(A96,'new total list'!B:B,1,false) -> Matthew Burton | K96: =IF(AND(ISNA(H96), ISNA(I96)), "Marked", "")
A97: =IFERROR(__xludf.DUMMYFUNCTION("""COMPUTED_VALUE"""),"Jeroen Mann") -> Jeroen Mann | B97: =IFERROR(__xludf.DUMMYFUNCTION("""COMPUTED_VALUE"""),"jeroen.mann@mannovation.nl") -> jeroen.mann@mannovation.nl | C97: =IFERROR(__xludf.DUMMYFUNCTION("""COMPUTED_VALUE"""),"Mannovation BV") -> Mannovation BV | D97: =IFERROR(__xludf.DUMMYFUNCTION("""COMPUTED_VALUE"""),"Directeur") -> Directeur | E97: =IFERROR(__xludf.DUMMYFUNCTION("""COMPUTED_VALUE"""),"Inspiration") -> Inspiration | F97: =IFERROR(__xludf.DUMMYFUNCTION("""COMPUTED_VALUE"""),"Maritime") -> Maritime | H97: =VLOOKUP(B97,'new total list'!E:E,1,false) -> jeroen.mann@mannovation.nl | I97: =vlookup(A97,'new total list'!B:B,1,false) -> Jeroen Mann | K97: =IF(AND(ISNA(H97), ISNA(I97)), "Marked", "")
A98: =IFERROR(__xludf.DUMMYFUNCTION("""COMPUTED_VALUE"""),"Arthur Kramer") -> Arthur Kramer | B98: =IFERROR(__xludf.DUMMYFUNCTION("""COMPUTED_VALUE"""),"a.kramer@visible-investments.nl") -> a.kramer@visible-investments.nl | C98: =IFERROR(__xludf.DUMMYFUNCTION("""COMPUTED_VALUE"""),"Visible investments") -> Visible investments | D98: =IFERROR(__xludf.DUMMYFUNCTION("""COMPUTED_VALUE"""),"GP") -> GP | E98: =IFERROR(__xludf.DUMMYFUNCTION("""COMPUTED_VALUE"""),"Possible investment opportunities") -> Possible investment opportunities | F98: =IFERROR(__xludf.DUMMYFUNCTION("""COMPUTED_VALUE"""),"Maritime") -> Maritime | H98: =VLOOKUP(B98,'new total list'!E:E,1,false) -> a.kramer@visible-investments.nl | I98: =vlookup(A98,'new total list'!B:B,1,false) -> Arthur Kramer | K98: =IF(AND(ISNA(H98), ISNA(I98)), "Marked", "")
A99: =IFERROR(__xludf.DUMMYFUNCTION("""COMPUTED_VALUE"""),"Haiyan Che") -> Haiyan Che | B99: =IFERROR(__xludf.DUMMYFUNCTION("""COMPUTED_VALUE"""),"yilunche@hotmail.com") -> yilunche@hotmail.com | C99: =IFERROR(__xludf.DUMMYFUNCTION("""COMPUTED_VALUE"""),"Outstanding Consulting Ltd.") -> Outstanding Consulting Ltd. | D99: =IFERROR(__xludf.DUMMYFUNCTION("""COMPUTED_VALUE"""),"Director") -> Director | E99: =IFERROR(__xludf.DUMMYFUNCTION("""COMPUTED_VALUE"""),"Networking") -> Networking | F99: =IFERROR(__xludf.DUMMYFUNCTION("""COMPUTED_VALUE"""),"Dual Use") -> Dual Use | H99: =VLOOKUP(B99,'new total list'!E:E,1,false) -> yilunche@hotmail.com | I99: =vlookup(A99,'new total list'!B:B,1,false) -> Haiyan Che | K99: =IF(AND(ISNA(H99), ISNA(I99)), "Marked", "")
A100: =IFERROR(__xludf.DUMMYFUNCTION("""COMPUTED_VALUE"""),"Ernst van der Wal") -> Ernst van der Wal | B100: =IFERROR(__xludf.DUMMYFUNCTION("""COMPUTED_VALUE"""),"ernst@lyla.systems") -> ernst@lyla.systems | C100: =IFERROR(__xludf.DUMMYFUNCTION("""COMPUTED_VALUE"""),"Lyla") -> Lyla | D100: =IFERROR(__xludf.DUMMYFUNCTION("""COMPUTED_VALUE"""),"Co-founder") -> Co-founder | E100: =IFERROR(__xludf.DUMMYFUNCTION("""COMPUTED_VALUE"""),"Investor connections") -> Investor connections | F100: =IFERROR(__xludf.DUMMYFUNCTION("""COMPUTED_VALUE"""),"meet other startups and experts in the medtech field") -> meet other startups and experts in the medtech field | H100: =VLOOKUP(B100,'new total list'!E:E,1,false) -> Ernst@lyla.systems | I100: =vlookup(A100,'new total list'!B:B,1,false) -> #N/A | K100: =IF(AND(ISNA(H100), ISNA(I100)), "Marked", "")
...

Sheet invite july
A3: / --- HTML met CID-logo --- const htmlMessage = `<!doctype html> <html> <div style="display:none; max-height:0; overflow:hidden; opacity:0; color:transparent;"> Join us from 14:00 for startup pitches, live demos, and networking at YES!Delft. </div> <head> <meta http-equiv="Content-Type" content="text/html; charset=UTF-8"> </head> <body style="margin:0;padding:0;font-family:Arial,Helvetica,sans-serif;line-height:1.5;color:#051B3F;"> <table role="presentation" border="0" cellpadding="0" cellspacing="0" width="100%"> <tr> <td style="padding:24px;"> <table role="presentation" border="0" cellpadding="0" cellspacing="0" width="100%" style="max-width:640px;"> <tr> <td style="font-family:Arial,Helvetica,sans-serif;line-height:1.5;color:#051B3F;"> <p>Dear ${row[2]},</p> <p>I am happy to invite you to our annual flagship event, Meet the Startups, the demo day of YES!Delft,<br> taking place on <strong>Thursday, October 8th, starting at 14:00</strong> at YES!Delft.</p> <p>During this event, the latest startups from YES!Delft will showcase their innovations through inspiring pitches and live demonstrations. ​Alongside the pitch sessions, guests can meet the startups directly at their stands, exchange ideas, explore collaboration opportunities, and connect with the wider YES!Delft ecosystem.</p> ${inviteExtraHtml} <p> <a href="${ticketUrl}" style=" display:inline-block; background-color:#1CBBED; color:#051B3F; padding:11px 22px; border-radius:4px; text-decoration:none; font-weight:bold; "> Get your tickets </a> <p>Your presence and insights can make a real difference as these entrepreneurs scale their ideas into impactful businesses.</p <p>I look forward to seeing you at Meet the Startups on October 8!</p>

Sheet Sheet21
A2: container for ápple' | B2: <body style="margin:0;padding:0;font-family:Arial,Helvetica,sans-serif;line-height:1.5;color:#051B3F;"> <table role="presentation" border="0" cellpadding="0" cellspacing="0" width="100%"> <tr> <td style="padding:24px;"> <table role="presentation" border="0" cellpadding="0" cellspacing="0" width="100%" style="max-width:720px;"> <tr> <td style="font-family:Arial,Helvetica,sans-serif;line-height:1.5;color:#051B3F;">

Sheet 20 yrs
A3: function sendEmails() {
A4: Logger.log("sendEmails started");
A5: var sheet = SpreadsheetApp.getActiveSpreadsheet().getSheetByName('new total list');
A6: var startRow = 3; // Start at third row because the first rows contains the data headers
A7: var lastRow = sheet.getLastRow();
A8: var numRows = lastRow - startRow + 1;
A10: Utilities.sleep(1000); // Sleep 1 second between each email
A12: if (numRows <= 0) {
A13: Logger.log("No data to process.");
A14: return; // Exit the function
A15: }
A16: var dataRange = sheet.getRange(startRow, 1, numRows, 12);
... A104: }

Sheet Sheet13
A3: function sendEmails() {
A4: Logger.log("sendEmails started");
A6: const sheet = SpreadsheetApp.getActiveSpreadsheet().getSheetByName('new total list');
A7: const startRow = 3;
A8: const LOGO_DRIVE_ID = '1dmyeWaKsmjky2ccewuwU0ZF22GNf6XC8'; // bestand-ID van je logo
A9: const logoBlob = DriveApp.getFileById(LOGO_DRIVE_ID).getBlob();
A11: const lastRow = sheet.getLastRow();
A12: const numRows = lastRow - startRow + 1;
A13: if (numRows <= 0) {
A14: Logger.log("No data to process.");
A15: return;
A16: }
... A110: }

Sheet Sheet12
A3: function sendEmails() {
A4: Logger.log("sendEmails started");
A5: var sheet = SpreadsheetApp.getActiveSpreadsheet().getSheetByName('new total list');
A6: var startRow = 3; // Start at third row because the first rows contains the data headers
A7: const LOGO_DRIVE_ID = '1Lk8PFYTknNiibBZ_hBibtYDMyfJcASs9'
A8: var lastRow = sheet.getLastRow();
A9: var numRows = lastRow - startRow + 1;
A10: // Haal logo-blob op voor inline CID
A11: const logoBlob = DriveApp.getFileById(LOGO_DRIVE_ID).getBlob();
A13: if (numRows <= 0) {
A14: Logger.log("No data to process.");
A15: return; // Exit the function
... A102: }
